Workbook

Sheet Income Statement
A1: Panera Bread Company
A3: Income Statement
A4: (in thousands of dollars)
D5: Historical | I5: Forecast
D6: Actual | E6: Actual | F6: Actual | G6: Actual | H6: Est (9/3)
D7: 2003 | E7: 2004 | F7: 2005 | G7: 2006 | H7: 2007 | I7: 2008 | J7: 2009 | K7: 2010 | L7: 2011 | M7: 2012
A8: Revenue
B9: Bakery- Café Sales | D9: 280050.54 | E9: 368937.03 | F9: 493011.75 | G9: 638307.67 | H9: 808500 | I9: =H9*(1+'Ratio & Assumptions'!I9) -> 768075 | J9: =I9*(1+'Ratio & Assumptions'!J9) -> 860244 | K9: =J9*(1+'Ratio & Assumptions'!K9) -> 989280.6 | L9: =K9*(1+'Ratio & Assumptions'!L9) -> 1162404.7 | M9: =L9*(1+'Ratio & Assumptions'!M9) -> 1423945.8
B10: Franchise Royalties and Fess | D10: 36370.2 | E10: 47913.9 | F10: 64027.5 | G10: 82897.1 | H10: 105000 | I10: =H10*(1+'Ratio & Assumptions'!I10) -> 99750 | J10: =I10*(1+'Ratio & Assumptions'!J10) -> 111720 | K10: =J10*(1+'Ratio & Assumptions'!K10) -> 128478 | L10: =K10*(1+'Ratio & Assumptions'!L10) -> 150961.65 | M10: =L10*(1+'Ratio & Assumptions'!M10) -> 184928.02
B11: Commissary Sales to Franchisees | D11: 47281.26 | E11: 62288.07 | F11: 83235.75 | G11: 107766.23 | H11: 136500 | I11: =H11*(1+'Ratio & Assumptions'!I11) -> 129675 | J11: =I11*(1+'Ratio & Assumptions'!J11) -> 145236 | K11: =J11*(1+'Ratio & Assumptions'!K11) -> 167021.4 | L11: =K11*(1+'Ratio & Assumptions'!L11) -> 196250.14 | M11: =L11*(1+'Ratio & Assumptions'!M11) -> 240406.43
D12: 363702 | E12: 479139 | F12: 640275 | G12: 828971 | H12: 1050000 | I12: =SUM(I9:I11) -> 997500 | J12: =SUM(J9:J11) -> 1117200 | K12: =SUM(K9:K11) -> 1284780 | L12: =SUM(L9:L11) -> 1509616.5 | M12: =SUM(M9:M11) -> 1849280.2
A13: Sales Growth | D13: 0.30944872 | E13: 0.31739446 | F13: 0.33630324 | G13: 0.29471087 | H13: 0.26663056 | I13: =(I12-H12)/H12 -> -0.05 | J13: =(J12-I12)/I12 -> 0.12 | K13: =(K12-J12)/J12 -> 0.15 | L13: =(L12-K12)/K12 -> 0.175 | M13: =(M12-L12)/L12 -> 0.225
A14: Bakery Cost of Sales
B15: Food | D15: 81214.657 | E15: 108836.42 | F15: 147903.52 | G15: 194683.84 | H15: 250635 | I15: =I9*'Ratio & Assumptions'!I16 -> 234262.88 | J15: =J9*'Ratio & Assumptions'!J16 -> 266675.64 | K15: =K9*'Ratio & Assumptions'!K16 -> 301730.58 | L15: =L9*'Ratio & Assumptions'!L16 -> 360345.46 | M15: =M9*'Ratio & Assumptions'!M16 -> 434303.46
B16: Labor | D16: 86815.667 | E16: 118059.85 | F16: 157763.76 | G16: 210641.53 | H16: 266805 | I16: =I9*'Ratio & Assumptions'!I17 -> 230422.5 | J16: =J9*'Ratio & Assumptions'!J17 -> 258073.2 | K16: =K9*'Ratio & Assumptions'!K17 -> 306676.99 | L16: =L9*'Ratio & Assumptions'!L17 -> 371969.51 | M16: =M9*'Ratio & Assumptions'!M17 -> 469902.1
B17: Occupancy | D17: 25000 | E17: 38000 | F17: 57000 | G17: 80000 | H17: 140000 | I17: =I9*'Ratio & Assumptions'!I18 -> 115211.25 | J17: =J9*'Ratio & Assumptions'!J18 -> 129036.6 | K17: =K9*'Ratio & Assumptions'!K18 -> 148392.09 | L17: =L9*'Ratio & Assumptions'!L18 -> 174360.71 | M17: =M9*'Ratio & Assumptions'!M18 -> 213591.86
B18: Other | D18: 17791.676 | E18: 23809.727 | F18: 37092.715 | G18: 57590.63 | H18: 80560 | I18: =I9*'Ratio & Assumptions'!I19 -> 76807.5 | J18: =J9*'Ratio & Assumptions'!J19 -> 86024.4 | K18: =J18*(1+'Ratio & Assumptions'!K19) -> 94626.84 | L18: =K18*(1+'Ratio & Assumptions'!L19) -> 104089.52 | M18: =L18*(1+'Ratio & Assumptions'!M19) -> 114498.48
A19: Total Cost of Goods Sold | D19: 210822 | E19: 288706 | F19: 399760 | G19: 542916 | H19: 738000 | I19: =SUM(I15:I18) -> 656704.12 | J19: =SUM(J15:J18) -> 739809.84 | K19: =SUM(K15:K18) -> 851426.5 | L19: =SUM(L15:L18) -> 1010765.2 | M19: =SUM(M15:M18) -> 1232295.9
B20: Bakery Gross Profit | D20: 69228.54 | E20: 80231.03 | F20: 93251.75 | G20: 95391.67 | H20: 70500 | I20: =I9-I19 -> 111370.88 | J20: =J9-J19 -> 120434.16 | K20: =K9-K19 -> 137854.1 | L20: =L9-L19 -> 151639.51 | M20: =M9-M19 -> 191649.86
A21: Bakery Gross Margin | D21: 0.24720017 | E21: 0.21746538 | F21: 0.18914711 | G21: 0.14944466 | H21: 0.087198516 | I21: =I20/I9 -> 0.145 | J21: =J20/J9 -> 0.14 | K21: =K20/K9 -> 0.13934783 | L21: =L20/L9 -> 0.13045328 | M21: =M20/M9 -> 0.1345907
A23: Commisary Cost of Sales | D23: 54967 | E23: 65627 | F23: 75036 | G23: 85618 | H23: 86000 | I23: =I11*'Ratio & Assumptions'!I21 -> 77805 | J23: =J11*'Ratio & Assumptions'!J21 -> 84236.88 | K23: =K11*'Ratio & Assumptions'!K21 -> 91861.77 | L23: =L11*'Ratio & Assumptions'!L21 -> 104012.58 | M23: =M11*'Ratio & Assumptions'!M21 -> 122607.28
B24: Commisary Gross Profit | D24: -7685.74 | E24: -3338.93 | F24: 8199.75 | G24: 22148.23 | H24: 50500 | I24: =I11-I23 -> 51870 | J24: =J11-J23 -> 60999.12 | K24: =K11-K23 -> 75159.63 | L24: =L11-L23 -> 92237.568 | M24: =M11-M23 -> 117799.15
A25: Commisary Gross Margin | D25: -0.16255362 | E25: -0.053604647 | F25: 0.098512358 | G25: 0.20552106 | H25: 0.36996337 | I25: =I24/I11 -> 0.4 | J25: =J24/J11 -> 0.42 | K25: =K24/K11 -> 0.45 | L25: =L24/L11 -> 0.47 | M25: =M24/M11 -> 0.49
A27: Depreciation & Amortization | D27: 18304 | E27: 25298 | F27: 33011 | G27: 44166 | H27: 60000 | I27: ='Ratio & Assumptions'!I38+'Ratio & Assumptions'!I40 -> 69379.333 | J27: ='Ratio & Assumptions'!J38+'Ratio & Assumptions'!J40 -> 77809.444 | K27: ='Ratio & Assumptions'!K38+'Ratio & Assumptions'!K40 -> 86734.37 | L27: ='Ratio & Assumptions'!L38+'Ratio & Assumptions'!L40 -> 95329.42 | M27: ='Ratio & Assumptions'!M38+'Ratio & Assumptions'!M40 -> 104144.39
A28: General and administrative | D28: 31502 | E28: 38735 | F28: 50240 | G28: 63502 | H28: 78000 | I28: =H28*(1+'Ratio & Assumptions'!I23) -> 93600 | J28: =I28*(1+'Ratio & Assumptions'!J23) -> 114660 | K28: =J28*(1+'Ratio & Assumptions'!K23) -> 143325 | L28: =K28*(1+'Ratio & Assumptions'!L23) -> 182739.38 | M28: =L28*(1+'Ratio & Assumptions'!M23) -> 237561.19
A29: EBIT | D29: 48107 | E29: 60773 | F29: 82228 | G29: 92769 | H29: 88000 | I29: =I12-I19-I23-I27-I28 -> 100011.54 | J29: =J12-J19-J23-J27-J28 -> 100683.84 | K29: =K12-K19-K23-K27-K28 -> 111432.36 | L29: =L12-L19-L23-L27-L28 -> 116769.93 | M29: =M12-M19-M23-M27-M28 -> 152671.46
A30: EBITDA | I30: =I29+I27 -> 169390.88 | J30: =J29+J27 -> 178493.28 | K30: =K29+K27 -> 198166.73 | L30: =L29+L27 -> 212099.35 | M30: =M29+M27 -> 256815.85
A31: Interest expense | D31: 48 | E31: 18 | F31: 50 | G31: 92 | H31: 150 | I31: 0 | J31: =I31*$I$36 -> 0 | K31: =J31*$I$36 -> 0 | L31: =K31*$I$36 -> 0 | M31: =L31*$I$36 -> 0
A32: Pretax profit | D32: 48059 | E32: 60755 | F32: 82178 | G32: 92677 | H32: 87850 | I32: =I29-I31 -> 100011.54 | J32: =J29-J31 -> 100683.84 | K32: =K29-K31 -> 111432.36 | L32: =L29-L31 -> 116769.93 | M32: =M29-M31 -> 152671.46
A33: Tax | D33: 17629 | E33: 22175 | F33: 29995 | G33: 33827 | H33: 31500 | I33: =I32*'Ratio & Assumptions'!I25 -> 37004.27 | J33: =J32*'Ratio & Assumptions'!J25 -> 37253.019 | K33: =K32*'Ratio & Assumptions'!K25 -> 41229.973 | L33: =L32*'Ratio & Assumptions'!L25 -> 43204.876 | M33: =M32*'Ratio & Assumptions'!M25 -> 56488.44
A34: Net income | D34: 30430 | E34: 38580 | F34: 52183 | G34: 58850 | H34: 56350 | I34: =I32-I33 -> 63007.271 | J34: =J32-J33 -> 63430.816 | K34: =K32-K33 -> 70202.387 | L34: =L32-L33 -> 73565.059 | M34: =M32-M33 -> 96183.019

Sheet Balance Sheet
A1: Panera Bread Company
A3: Balance Sheet
A4: (in thousands of dollars)
D5: Historical | I5: Forecast
D6: Actual | E6: Actual | F6: Actual | G6: Actual | H6: Est (9/3)
D7: 2003 | E7: 2004 | F7: 2005 | G7: 2006 | H7: 2007 | I7: 2008 | J7: 2009 | K7: 2010 | L7: 2011 | M7: 2012
A8: Assets
B9: Current Assets
C10: Cash | D10: 51421 | E10: 58054 | F10: 60651 | G10: 72122 | H10: 89316 | I10: =H10+'Cash Flow Statement'!E23 -> 89316 | J10: =I10+'Cash Flow Statement'!F23 -> 89316 | K10: =J10+'Cash Flow Statement'!G23 -> 89316 | L10: =K10+'Cash Flow Statement'!H23 -> 89316 | M10: =L10+'Cash Flow Statement'!I23 -> 152556.49
C11: A/R | D11: 12394 | E11: 17256 | F11: 25158 | G11: 30919 | H11: 36792 | I11: =(SUM('Income Statement'!I10:I11)/365)*'Ratio & Assumptions'!I30 -> 37713.699 | J11: =(SUM('Income Statement'!J10:J11)/365)*'Ratio & Assumptions'!J30 -> 42239.342 | K11: =(SUM('Income Statement'!K10:K11)/365)*'Ratio & Assumptions'!K30 -> 48575.244 | L11: =(SUM('Income Statement'!L10:L11)/365)*'Ratio & Assumptions'!L30 -> 57075.912 | M11: =(SUM('Income Statement'!M10:M11)/365)*'Ratio & Assumptions'!M30 -> 69917.992
C12: Inventory | D12: 4350 | E12: 5398 | F12: 7358 | G12: 8714 | H12: 11394 | I12: =(('Income Statement'!H15+'Income Statement'!H23)/365)*'Ratio & Assumptions'!I31 -> 10145.164 | J12: =(('Income Statement'!I15+'Income Statement'!I23)/365)*'Ratio & Assumptions'!J31 -> 10259.766 | K12: =(('Income Statement'!J15+'Income Statement'!J23)/365)*'Ratio & Assumptions'!K31 -> 10575.446 | L12: =(('Income Statement'!K15+'Income Statement'!K23)/365)*'Ratio & Assumptions'!L31 -> 12940.023 | M12: =(('Income Statement'!L15+'Income Statement'!L23)/365)*'Ratio & Assumptions'!M31 -> 13994.352
C13: Prepaid & Other | D13: 3887 | E13: 3905 | F13: 9607 | G13: 15863 | H13: 12498 | I13: =((('Income Statement'!I12-'Income Statement'!I29)+'Income Statement'!I27)/365)*'Ratio & Assumptions'!I32 -> 13244.764 | J13: =((('Income Statement'!J12-'Income Statement'!J29)+'Income Statement'!J27)/365)*'Ratio & Assumptions'!J32 -> 14990.762 | K13: =((('Income Statement'!K12-'Income Statement'!K29)+'Income Statement'!K27)/365)*'Ratio & Assumptions'!K32 -> 17261.397 | L13: =((('Income Statement'!L12-'Income Statement'!L29)+'Income Statement'!L27)/365)*'Ratio & Assumptions'!L32 -> 20385.972 | M13: =((('Income Statement'!M12-'Income Statement'!M29)+'Income Statement'!M27)/365)*'Ratio & Assumptions'!M32 -> 24667.851
D14: 72052 | E14: 84613 | F14: 102774 | G14: 127618 | H14: 150000 | I14: =SUM(I10:I13) -> 150419.63 | J14: =SUM(J10:J13) -> 156805.87 | K14: =SUM(K10:K13) -> 165728.09 | L14: =SUM(L10:L13) -> 179717.91 | M14: =SUM(M10:M13) -> 261136.68
A16: Property, plant, and equipment | E16: 289601 | F16: 387104 | G16: 504420 | H16: 636650 | I16: =H16+'Ratio & Assumptions'!I36 -> 786650 | J16: =I16+'Ratio & Assumptions'!J36 -> 942650 | K16: =J16+'Ratio & Assumptions'!K36 -> 1107650 | L16: =K16+'Ratio & Assumptions'!L36 -> 1284650 | M16: =L16+'Ratio & Assumptions'!M36 -> 1470650
B17: Accumulated Depreciation | E17: -87876 | F17: -118295 | G17: -158443 | H17: -206650 | I17: =H17-'Ratio & Assumptions'!I38 -> -264029.33 | J17: =I17-'Ratio & Assumptions'!J38 -> -329838.78 | K17: =J17-'Ratio & Assumptions'!K38 -> -404573.15 | L17: =K17-'Ratio & Assumptions'!L38 -> -487902.57 | M17: =L17-'Ratio & Assumptions'!M38 -> -580046.95
A18: Property, plant, and equipment, net | D18: 146362 | E18: 201725 | F18: 268809 | G18: 345977 | H18: 430000 | I18: =SUM(I16:I17) -> 522620.67 | J18: =SUM(J16:J17) -> 612811.22 | K18: =SUM(K16:K17) -> 703076.85 | L18: =SUM(L16:L17) -> 796747.43 | M18: =SUM(M16:M17) -> 890603.05
A20: Goodwill and other assets | D20: 38421 | E20: 38334 | F20: 66084 | G20: 69014 | H20: 110000 | I20: =H20-'Ratio & Assumptions'!I40 -> 98000 | J20: =I20-'Ratio & Assumptions'!J40 -> 86000 | K20: =J20-'Ratio & Assumptions'!K40 -> 74000 | L20: =K20-'Ratio & Assumptions'!L40 -> 62000 | M20: =L20-'Ratio & Assumptions'!M40 -> 50000
D21: 256835 | E21: 324672 | F21: 437667 | G21: 542609 | H21: 690000 | I21: =SUM(I20+I18+I14) -> 771040.29 | J21: =SUM(J20+J18+J14) -> 855617.09 | K21: =SUM(K20+K18+K14) -> 942804.94 | L21: =SUM(L20+L18+L14) -> 1038465.3 | M21: =SUM(M20+M18+M14) -> 1201739.7
A23: Operating liabilities
A24: Current liabilities | D24: 45643 | E24: 55705 | F24: 86865 | G24: 109610 | H24: 130000 | I24: =(('Income Statement'!I12-'Income Statement'!I29+'Income Statement'!I27)/365)*'Ratio & Assumptions'!I33 -> 132447.64 | J24: =(('Income Statement'!J12-'Income Statement'!J29+'Income Statement'!J27)/365)*'Ratio & Assumptions'!J33 -> 149907.62 | K24: =(('Income Statement'!K12-'Income Statement'!K29+'Income Statement'!K27)/365)*'Ratio & Assumptions'!K33 -> 172613.97 | L24: =(('Income Statement'!L12-'Income Statement'!L29+'Income Statement'!L27)/365)*'Ratio & Assumptions'!L33 -> 203859.72 | M24: =(('Income Statement'!M12-'Income Statement'!M29+'Income Statement'!M27)/365)*'Ratio & Assumptions'!M33 -> 246678.51
A25: Deferred rent and other liabilities | D25: 13616 | E25: 27604 | F25: 33824 | G25: 35333 | H25: 45000 | I25: =H25*(1+'Ratio & Assumptions'!I35) -> 57150 | J25: =I25*(1+'Ratio & Assumptions'!J35) -> 72580.5 | K25: =J25*(1+'Ratio & Assumptions'!K35) -> 92177.235 | L25: =K25*(1+'Ratio & Assumptions'!L35) -> 117065.09 | M25: =L25*(1+'Ratio & Assumptions'!M35) -> 148672.66
D26: 59259 | E26: 83309 | F26: 120689 | G26: 144943 | H26: 175000 | I26: =SUM(I24:I25) -> 189597.64 | J26: =SUM(J24:J25) -> 222488.12 | K26: =SUM(K24:K25) -> 264791.21 | L26: =SUM(L24:L25) -> 320924.81 | M26: =SUM(M24:M25) -> 395351.17
A28: Debt | D28: 0 | E28: 0 | F28: 0 | G28: 0 | H28: 75000 | I28: =H28+SUM('Cash Flow Statement'!E21:E22) -> 78435.38 | J28: =I28+SUM('Cash Flow Statement'!F21:F22) -> 66690.887 | K28: =J28+SUM('Cash Flow Statement'!G21:G22) -> 41373.255 | L28: =K28+SUM('Cash Flow Statement'!H21:H22) -> 7334.9925 | M28: =L28+SUM('Cash Flow Statement'!I21:I22) -> 0
A29: Equity | D29: 197576 | E29: 241363 | F29: 316978 | G29: 397666 | H29: 440000 | I29: =H29+'Income Statement'!I34 -> 503007.27 | J29: =I29+'Income Statement'!J34 -> 566438.09 | K29: =J29+'Income Statement'!K34 -> 636640.47 | L29: =K29+'Income Statement'!L34 -> 710205.53 | M29: =L29+'Income Statement'!M34 -> 806388.55
A30: Total liabilities and equity | D30: 256835 | E30: 324672 | F30: 437667 | G30: 542609 | H30: =H26+H28+H29 -> 690000 | I30: =SUM(I26:I29) -> 771040.29 | J30: =SUM(J26:J29) -> 855617.09 | K30: =SUM(K26:K29) -> 942804.94 | L30: =SUM(L26:L29) -> 1038465.3 | M30: =SUM(M26:M29) -> 1201739.7
C31: Check | D31: 0 | E31: 0 | F31: 0 | G31: 0 | H31: 0 | I31: =I21-I30 -> 0 | J31: =J21-J30 -> 0 | K31: =K21-K30 -> 0 | L31: =L21-L30 -> 0 | M31: =M21-M30 -> 0

Sheet Cash Flow Statement
E3: 2008 | F3: =E3+1 -> 2009 | G3: =F3+1 -> 2010 | H3: =G3+1 -> 2011 | I3: =H3+1 -> 2012
C5: Net Income | E5: ='Income Statement'!I34 -> 63007.271 | F5: ='Income Statement'!J34 -> 63430.816 | G5: ='Income Statement'!K34 -> 70202.387 | H5: ='Income Statement'!L34 -> 73565.059 | I5: ='Income Statement'!M34 -> 96183.019
C7: Operating Activities
C8: Depreciation + Amortization | E8: ='Income Statement'!I27 -> 69379.333 | F8: ='Income Statement'!J27 -> 77809.444 | G8: ='Income Statement'!K27 -> 86734.37 | H8: ='Income Statement'!L27 -> 95329.42 | I8: ='Income Statement'!M27 -> 104144.39
C9: Change in NWC
C11: A/R | E11: ='Balance Sheet'!H11-'Balance Sheet'!I11 -> -921.69863 | F11: ='Balance Sheet'!I11-'Balance Sheet'!J11 -> -4525.6438 | G11: ='Balance Sheet'!J11-'Balance Sheet'!K11 -> -6335.9014 | H11: ='Balance Sheet'!K11-'Balance Sheet'!L11 -> -8500.6677 | I11: ='Balance Sheet'!L11-'Balance Sheet'!M11 -> -12842.08
C12: Inventory (Decrease, (increase)) | E12: ='Balance Sheet'!H12-'Balance Sheet'!I12 -> 1248.8356 | F12: ='Balance Sheet'!I12-'Balance Sheet'!J12 -> -114.60137 | G12: ='Balance Sheet'!J12-'Balance Sheet'!K12 -> -315.68005 | H12: ='Balance Sheet'!K12-'Balance Sheet'!L12 -> -2364.5768 | I12: ='Balance Sheet'!L12-'Balance Sheet'!M12 -> -1054.3292
C13: A/P ((decrease), increase) | E13: ='Balance Sheet'!I24-'Balance Sheet'!H24 -> 2447.6427 | F13: ='Balance Sheet'!J24-'Balance Sheet'!I24 -> 17459.975 | G13: ='Balance Sheet'!K24-'Balance Sheet'!J24 -> 22706.356 | H13: ='Balance Sheet'!L24-'Balance Sheet'!K24 -> 31245.75 | I13: ='Balance Sheet'!M24-'Balance Sheet'!L24 -> 42818.788
C14: Prepaid expenses | E14: ='Balance Sheet'!H13-'Balance Sheet'!I13 -> -746.76427 | F14: ='Balance Sheet'!I13-'Balance Sheet'!J13 -> -1745.9975 | G14: ='Balance Sheet'!J13-'Balance Sheet'!K13 -> -2270.6356 | H14: ='Balance Sheet'!K13-'Balance Sheet'!L13 -> -3124.575 | I14: ='Balance Sheet'!L13-'Balance Sheet'!M13 -> -4281.8788
C15: Deferred Revenue | E15: ='Balance Sheet'!I25-'Balance Sheet'!H25 -> 12150 | F15: ='Balance Sheet'!J25-'Balance Sheet'!I25 -> 15430.5 | G15: ='Balance Sheet'!K25-'Balance Sheet'!J25 -> 19596.735 | H15: ='Balance Sheet'!L25-'Balance Sheet'!K25 -> 24887.853 | I15: ='Balance Sheet'!M25-'Balance Sheet'!L25 -> 31607.574
C17: CAPEX | E17: =-'Ratio & Assumptions'!I36 -> -150000 | F17: =-'Ratio & Assumptions'!J36 -> -156000 | G17: =-'Ratio & Assumptions'!K36 -> -165000 | H17: =-'Ratio & Assumptions'!L36 -> -177000 | I17: =-'Ratio & Assumptions'!M36 -> -186000
C18: Increase in other long-term assets
C19: Cash Flow Available | E19: =SUM(E5:E17) -> -3435.38 | F19: =SUM(F5:F17) -> 11744.493 | G19: =SUM(G5:G17) -> 25317.632 | H19: =SUM(H5:H17) -> 34038.263 | I19: =SUM(I5:I17) -> 70575.48
C21: Debt Pay Down | E21: =IF(E22>0,0,IF(E25>E19,-E19,-E25)) -> 0 | F21: =IF(F22>0,0,IF(F25>F19,-F19,-F25)) -> -11744.493 | G21: =IF(G22>0,0,IF(G25>G19,-G19,-G25)) -> -25317.632 | H21: =IF(H22>0,0,IF(H25>H19,-H19,-H25)) -> -34038.263 | I21: =IF(I22>0,0,IF(I25>I19,-I19,-I25)) -> -7334.9925
C22: Debt Borrowings | E22: =IF(E19<0,-E19, 0) -> 3435.38 | F22: =IF(F19<0,-F19, 0) -> 0 | G22: =IF(G19<0,-G19, 0) -> 0 | H22: =IF(H19<0,-H19, 0) -> 0 | I22: =IF(I19<0,-I19, 0) -> 0
C23: Increase in Cash | E23: =SUM(E19:E22) -> 0 | F23: =SUM(F19:F22) -> 0 | G23: =SUM(G19:G22) -> 0 | H23: =SUM(H19:H22) -> 0 | I23: =SUM(I19:I22) -> 63240.488
C25: Debt Balance | E25: ='Balance Sheet'!H28 -> 75000 | F25: ='Balance Sheet'!I28 -> 78435.38 | G25: ='Balance Sheet'!J28 -> 66690.887 | H25: ='Balance Sheet'!K28 -> 41373.255 | I25: ='Balance Sheet'!L28 -> 7334.9925

Sheet Ratio & Assumptions
A1: Panera Bread Company
A3: Ratios & Assumptions
A4: (in thousands of dollars)
D5: Historical | I5: Forecast
D6: Actual | E6: Actual | F6: Actual | G6: Actual | H6: Est (9/3)
D7: 2003 | E7: 2004 | F7: 2005 | G7: 2006 | H7: 2007 | I7: 2008 | J7: 2009 | K7: 2010 | L7: 2011 | M7: 2012
A9: Sales Growth | D9: 0.30944872 | E9: 0.31739446 | F9: 0.33630324 | G9: 0.29471087 | H9: 0.26663056 | I9: -0.05 | J9: 0.12 | K9: 0.15 | L9: 0.175 | M9: 0.225
B10: Bakery- Café Sales | D10: 0.30944872 | E10: 0.31739446 | F10: 0.33630324 | G10: 0.29471087 | H10: 0.26663056 | I10: =I9 -> -0.05 | J10: =J9 -> 0.12 | K10: =K9 -> 0.15 | L10: =L9 -> 0.175 | M10: =M9 -> 0.225
B11: Franchise Royalties and Fess | D11: 0.30944872 | E11: 0.31739446 | F11: 0.33630324 | G11: 0.29471087 | H11: 0.26663056 | I11: =I10 -> -0.05 | J11: =J10 -> 0.12 | K11: =K10 -> 0.15 | L11: =L10 -> 0.175 | M11: =M10 -> 0.225
B12: Commissary Sales to Franchisees | D12: 0.30944872 | E12: 0.31739446 | F12: 0.33630324 | G12: 0.29471087 | H12: 0.26663056 | I12: =I11 -> -0.05 | J12: =J11 -> 0.12 | K12: =K11 -> 0.15 | L12: =L11 -> 0.175 | M12: =M11 -> 0.225
A15: Bakery Cost of Sales
B16: Food | D16: 0.29 | E16: 0.295 | F16: 0.3 | G16: 0.305 | H16: 0.31 | I16: 0.305 | J16: 0.31 | K16: 0.305 | L16: 0.31 | M16: 0.305
B17: Labor | D17: 0.31 | E17: 0.32 | F17: 0.32 | G17: 0.33 | H17: 0.33 | I17: 0.3 | J17: 0.3 | K17: 0.31 | L17: 0.32 | M17: 0.33
B18: Occupancy | D18: 0.089269601 | E18: 0.10299861 | F18: 0.11561591 | G18: 0.12533141 | H18: 0.17316017 | I18: 0.15 | J18: =I18 -> 0.15 | K18: =J18 -> 0.15 | L18: =K18 -> 0.15 | M18: =L18 -> 0.15
B19: Other | D19: 0.063530233 | E19: 0.064536017 | F19: 0.07523698 | G19: 0.090223935 | H19: 0.099641311 | I19: 0.1 | J19: 0.1 | K19: 0.1 | L19: 0.1 | M19: 0.1
A21: Commisary Cost of Sales | D21: 1.1625536 | E21: 1.0536046 | F21: 0.90148764 | G21: 0.79447894 | H21: ='Income Statement'!H23/'Income Statement'!H11 -> 0.63003663 | I21: 0.6 | J21: 0.58 | K21: 0.55 | L21: 0.53 | M21: 0.51
A23: General and administrative growth | D23: 0.26078604 | E23: 0.22960447 | F23: 0.2970182 | G23: 0.26397293 | H23: 0.22830777 | I23: 0.2 | J23: 0.225 | K23: 0.25 | L23: 0.275 | M23: 0.3
A25: Effective Tax Rate | D25: 0.36681995 | E25: 0.36499054 | F25: 0.36500037 | G25: 0.36499887 | H25: 0.35856574 | I25: 0.37 | J25: =I25 -> 0.37 | K25: =J25 -> 0.37 | L25: =K25 -> 0.37 | M25: =L25 -> 0.37
A27: Working Capital
B28: Cash Balance Needed
B29: A/R Days Total | D29: 12.438232 | E29: 13.145329 | F29: 14.341759 | G29: 13.613787 | H29: 13.613787 | I29: 14 | J29: =I29 -> 14 | K29: =J29 -> 14 | L29: =K29 -> 14 | M29: =L29 -> 14
B30: A/R Days Franchise | D30: 54.079271 | E30: 57.153606 | F30: 62.355476 | G30: 59.19038 | H30: 59.19038 | I30: 60 | J30: =I30 -> 60 | K30: =J30 -> 60 | L30: =K30 -> 60 | M30: =L30 -> 60
B31: Inventory | D31: 11.659059 | E31: 11.293313 | F31: 12.04663 | G31: 11.347089 | H31: 12.354063 | I31: 11 | J31: 12 | K31: 11 | L31: 12 | M31: 11
B32: Prepaid & Other | D32: 4.2490544 | E32: 3.2126226 | F32: 5.932675 | G32: 7.41957 | H32: 4.4635714 | I32: 5 | J32: 5 | K32: 5 | L32: 5 | M32: 5
B33: A/P and Accrual Days | D33: 49.894414 | E33: 45.828206 | F33: 53.642324 | G33: 51.267671 | H33: 46.428571 | I33: 50 | J33: =I33 -> 50 | K33: =J33 -> 50 | L33: =K33 -> 50 | M33: =L33 -> 50
A35: Deferred Rent and Other Liab | E35: 1.0273208 | F35: 0.22532966 | G35: 0.044613292 | H35: 0.27359692 | I35: 0.27 | J35: 0.27 | K35: 0.27 | L35: 0.27 | M35: 0.27
A36: CAPEX | D36: N/A | E36: N/A | F36: 97503 | G36: 117316 | H36: 132230 | I36: =120*I44 -> 150000 | J36: =120*J44 -> 156000 | K36: =120*K44 -> 165000 | L36: =120*L44 -> 177000 | M36: =120*M44 -> 186000
A38: Depreciation | D38: N/A | E38: N/A | F38: 30419 | G38: 40148 | H38: 48207 | I38: =_xlfn.FORECAST.LINEAR(I7,F38:H38,F7:H7) -> 57379.333 | J38: =_xlfn.FORECAST.LINEAR(J7,G38:I38,G7:I7) -> 65809.444 | K38: =_xlfn.FORECAST.LINEAR(K7,H38:J38,H7:J7) -> 74734.37 | L38: =_xlfn.FORECAST.LINEAR(L7,I38:K38,I7:K7) -> 83329.42 | M38: =_xlfn.FORECAST.LINEAR(M7,J38:L38,J7:L7) -> 92144.387
A39: Depreciation Avg Yrs | F39: 12.725731 | G39: 12.564013 | H39: 13.206588 | I39: 6 | J39: =I39 -> 6 | K39: =J39 -> 6 | L39: =K39 -> 6 | M39: =L39 -> 6
A40: Amortization | D40: N/A | E40: N/A | F40: 2592 | G40: 4018 | H40: 11793 | I40: 12000 | J40: =I40 -> 12000 | K40: =J40 -> 12000 | L40: =K40 -> 12000 | M40: =L40 -> 12000
A42: Debt Borrowing Rate
I43: Expected store count
I44: 1250 | J44: 1300 | K44: 1375 | L44: 1475 | M44: 1550
