Workbook
Name avgint: '[1]LBO Model'!$K$37
Name fincase: '[1]LBO Model'!$K$6
Name tax: '[1]LBO Model'!$K$16

Sheet LBO Model Base Case
A1: Luke Buddie, Gennaro Di Mauro, Peter Spira, Caden Carney
B2: Step 1: Outline everything you know
B3: Williams-Sonoma, Inc., LBO: Let’s Get Cooking
B4: Assumptions
B6: 2024 EBITDA | D6: ='Ex 10 Projections'!E18 -> 1438.43 | E6: Exhibit 10 | H6: Exit multiple | I6: =D12 -> 7.5
B7: SOFR | D7: 0.03 | H7: Number of shares outstanding (in millions) | I7: ='Ex 11 Comps'!I16 -> 64.2 | J7: Exhibit 11
B8: Tax rate | D8: 0.23 | E8: Exhibit 10 | H8: Current enterprise value | I8: =('Ex 11 Comps'!I16*'Ex 11 Comps'!J16)+'Ex 11 Comps'!K16 -> 8758.648 | J8: Equity Value + Debt Value
B9: Opening Balance Cash | D9: 0 | E9: Exhibit 9 - Case
B11: Financing Package | E11: Amount | F11: Cash Interest | G11: PIK | H11: Target Leverage (between 4-6) | J11: SOFR +
B12: Purchase multiple | D12: =SUM(D13:D16) -> 7.5 | E12: =D6*D12 -> 10788.225
B13: Term A | D13: 2.5 | E13: =D13*$D$6 -> 3596.075 | F13: =D7+J13 -> 0.055 | H13: =(E13+E14)/E29 -> 3.5 | J13: 0.025
B14: Term B | D14: 1 | E14: =D14*$D$6 -> 1438.43 | F14: =D7+J14 -> 0.075 | J14: 0.045
B15: Mezzanine (Cavalier Capital) | D15: 2 | E15: =D15*$D$6 -> 2876.86 | F15: 0.11 | G15: 0.02 | J15: Minimum Priciple
B16: Equity investment (Jeffereson Capital Management) | D16: 2 | E16: =E12-E13-E14-E15 -> 2876.86 | J16: 0.05
B19: Step 2: How/Who are you going to pay down your debt with your free cash flow?
B20: Williams-Sonoma, Inc., LBO: Let’s Get Cooking
B21: Debt-Repayment Schedule | K21: Target Leverage
K22: Debt/EBITDA: 4-6x
D23: 2023 | E23: 2024 | F23: 2025 | G23: 2026 | H23: 2027 | I23: 2028
B24: ='Ex 10 Projections'!B11 -> Total revenue | D24: ='Ex 10 Projections'!D11 -> 8674.42 | E24: ='Ex 10 Projections'!E11 -> 8471 | F24: ='Ex 10 Projections'!F11 -> 8553 | G24: ='Ex 10 Projections'!G11 -> 8862.29 | H24: ='Ex 10 Projections'!H11 -> 9181.33 | I24: ='Ex 10 Projections'!I11 -> 9582.61
B25: ='Ex 10 Projections'!B12 -> Cost of goods sold | D25: ='Ex 10 Projections'!D12 -> 4996.68 | E25: ='Ex 10 Projections'!E12 -> 5067.8 | F25: ='Ex 10 Projections'!F12 -> 5082.1 | G25: ='Ex 10 Projections'!G12 -> 5241.16 | H25: ='Ex 10 Projections'!H12 -> 5407.8 | I25: ='Ex 10 Projections'!I12 -> 5605.83
B26: ='Ex 10 Projections'!B13 -> Gross profit | D26: =D24-D25 -> 3677.74 | E26: =E24-E25 -> 3403.2 | F26: =F24-F25 -> 3470.9 | G26: =G24-G25 -> 3621.13 | H26: =H24-H25 -> 3773.53 | I26: =I24-I25 -> 3976.78
B27: ='Ex 10 Projections'!B14 -> Selling, general, and administrative expenses | D27: ='Ex 10 Projections'!D14 -> 2179.31 | E27: ='Ex 10 Projections'!E14 -> 2189.6 | F27: ='Ex 10 Projections'!F14 -> 2223.7 | G27: ='Ex 10 Projections'!G14 -> 2395.05 | H27: ='Ex 10 Projections'!H14 -> 2313.43 | I27: ='Ex 10 Projections'!I14 -> 2443.78
B28: ='Ex 10 Projections'!B17 -> Depreciation and amortization | D28: ='Ex 10 Projections'!D17 -> 214.2 | E28: ='Ex 10 Projections'!E17 -> 224.83 | F28: ='Ex 10 Projections'!F17 -> 233.48 | G28: ='Ex 10 Projections'!G17 -> 250.75 | H28: ='Ex 10 Projections'!H17 -> 252.51 | I28: ='Ex 10 Projections'!I17 -> 263.87
B29: ='Ex 10 Projections'!B18 -> EBITDA | D29: =(D26-D27+D28) -> 1712.63 | E29: =(E26-E27+E28) -> 1438.43 | F29: =(F26-F27+F28) -> 1480.68 | G29: =(G26-G27+G28) -> 1476.83 | H29: =(H26-H27+H28) -> 1712.61 | I29: =(I26-I27+I28) -> 1796.87
B30: Haircut to EBITDA (difference from expected EBITDA vs. realitstic) | C30: 0 | D30: =D29*(1+$C$30) -> 1712.63 | E30: =E29*(1+$C$30) -> 1438.43 | F30: =F29*(1+$C$30) -> 1480.68 | G30: =G29*(1+$C$30) -> 1476.83 | H30: =H29*(1+$C$30) -> 1712.61 | I30: =I29*(1+$C$30) -> 1796.87
B32: ='Ex 10 Projections'!B15 -> Operating income (EBIT) | D32: =D30-D28 -> 1498.43 | E32: =E30-E28 -> 1213.6 | F32: =F30-F28 -> 1247.2 | G32: =G30-G28 -> 1226.08 | H32: =H30-H28 -> 1460.1 | I32: =I30-I28 -> 1533
B33: ='Ex 10 Projections'!B22 -> CAPEX | D33: ='Ex 10 Projections'!D22 -> 354.1 | E33: ='Ex 10 Projections'!E22 -> 249.4 | F33: ='Ex 10 Projections'!F22 -> 262.31 | G33: ='Ex 10 Projections'!G22 -> 263.81 | H33: ='Ex 10 Projections'!H22 -> 320.49 | I33: ='Ex 10 Projections'!I22 -> 345.07
B34: ='Ex 10 Projections'!B23 -> Change in net working capital (NWC) | D34: ='Ex 10 Projections'!D23 -> -152.6 | E34: ='Ex 10 Projections'!E23 -> 227.87 | F34: ='Ex 10 Projections'!F23 -> 6.07 | G34: ='Ex 10 Projections'!G23 -> 22.91 | H34: ='Ex 10 Projections'!H23 -> 23.63 | I34: ='Ex 10 Projections'!I23 -> 29.72
B36: FCF | E36: =E32*(1-$D$8)+E28-E33-E34 -> 682.032 | F36: =F32*(1-$D$8)+F28-F33-F34 -> 925.444 | G36: =G32*(1-$D$8)+G28-G33-G34 -> 908.1116 | H36: =H32*(1-$D$8)+H28-H33-H34 -> 1032.667 | I36: =I32*(1-$D$8)+I28-I33-I34 -> 1069.49
B37: Beginning Balance | E37: =E13 -> 3596.075 | F37: =E37-E38 -> 3416.2713 | G37: =F37-F38 -> 3236.4675 | H37: =G37-G38 -> 3056.6638 | I37: =H37-H38 -> 2876.86
B38: Term A Principal | E38: =$J$16*$E$37 -> 179.80375 | F38: =$J$16*$E$37 -> 179.80375 | G38: =$J$16*$E$37 -> 179.80375 | H38: =$J$16*$E$37 -> 179.80375 | I38: =$J$16*$E$37 -> 179.80375
B39: Interest | E39: =$F$13*E37 -> 197.78413 | F39: =$F$13*F37 -> 187.89492 | G39: =$F$13*G37 -> 178.00571 | H39: =$F$13*H37 -> 168.11651 | I39: =$F$13*I37 -> 158.2273
B41: Total Debt | E41: =E38+E39 -> 377.58788 | F41: =F38+F39 -> 367.69867 | G41: =G38+G39 -> 357.80946 | H41: =H38+H39 -> 347.92026 | I41: =I38+I39 -> 338.03105
B42: Tax shield | E42: =E39*$D$8 -> 45.490349 | F42: =F39*$D$8 -> 43.215831 | G42: =G39*$D$8 -> 40.941314 | H42: =H39*$D$8 -> 38.666796 | I42: =I39*$D$8 -> 36.392279
B43: Excess Cash Flow | E43: =E36-E41+E42 -> 349.93447 | F43: =F36-F41+F42 -> 600.96116 | G43: =G36-G41+G42 -> 591.24345 | H43: =H36-H41+H42 -> 723.41354 | I43: =I36-I41+I42 -> 767.85123
B44: FCC | E44: =(E41+E43)/E41 -> 1.926763 | F44: =(F41+F43)/F41 -> 2.6343849 | G44: =(G41+G43)/G41 -> 2.6523975 | H44: =(H41+H43)/H41 -> 3.079251 | I44: =(I41+I43)/I41 -> 3.2715405
B46: Term B
B47: FCF | E47: =E43 -> 349.93447 | F47: =F43 -> 600.96116 | G47: =G43 -> 591.24345 | H47: =H43 -> 723.41354 | I47: =I43 -> 767.85123
B48: No principal
B49: Interest | E49: =$F$14*$E$14 -> 107.88225 | F49: =$F$14*$E$14 -> 107.88225 | G49: =$F$14*$E$14 -> 107.88225 | H49: =$F$14*$E$14 -> 107.88225 | I49: =$F$14*$E$14 -> 107.88225
B51: Total Debt | E51: =E49 -> 107.88225 | F51: =F49 -> 107.88225 | G51: =G49 -> 107.88225 | H51: =H49 -> 107.88225 | I51: =I49 -> 107.88225
B52: Tax Shield | E52: =E49*$D$8 -> 24.812918 | F52: =F49*$D$8 -> 24.812918 | G52: =G49*$D$8 -> 24.812918 | H52: =H49*$D$8 -> 24.812918 | I52: =I49*$D$8 -> 24.812918
B53: Excess | E53: =E47-E51+E52 -> 266.86514 | F53: =F47-F51+F52 -> 517.89183 | G53: =G47-G51+G52 -> 508.17412 | H53: =H47-H51+H52 -> 640.34421 | I53: =I47-I51+I52 -> 684.7819
B54: FCC | E54: =(E51+E53)/E51 -> 3.4736705 | F54: =(F51+F53)/F51 -> 5.8005286 | G54: =(G51+G53)/G51 -> 5.7104516 | H54: =(H51+H53)/H51 -> 6.9355845 | I54: =(I51+I53)/I51 -> 7.3474936
B56: Mezzanine | E56: =E53 -> 266.86514 | F56: =F53 -> 517.89183 | G56: =G53 -> 508.17412 | H56: =H53 -> 640.34421 | I56: =I53 -> 684.7819
B57: Interest | E57: =$F$15*$E$15 -> 316.4546 | F57: =$F$15*$E$15 -> 316.4546 | G57: =$F$15*$E$15 -> 316.4546 | H57: =$F$15*$E$15 -> 316.4546 | I57: =$F$15*$E$15 -> 316.4546
B58: Total Debt | E58: =E57 -> 316.4546 | F58: =F57 -> 316.4546 | G58: =G57 -> 316.4546 | H58: =H57 -> 316.4546 | I58: =I57 -> 316.4546
B59: Tax Shield | E59: =E58*$D$8 -> 72.784558 | F59: =F58*$D$8 -> 72.784558 | G59: =G58*$D$8 -> 72.784558 | H59: =H58*$D$8 -> 72.784558 | I59: =I58*$D$8 -> 72.784558
B60: Excess | E60: =E56-E58+E59 -> 23.195099 | F60: =F56-F58+F59 -> 274.22179 | G60: =G56-G58+G59 -> 264.50408 | H60: =H56-H58+H59 -> 396.67417 | I60: =I56-I58+I59 -> 441.11185
B61: FCC | E61: =(E60+E58)/E58 -> 1.0732968 | F61: =(F60+F58)/F58 -> 1.8665439 | G61: =(G60+G58)/G58 -> 1.8358358 | H61: =(H60+H58)/H58 -> 2.2534947 | I61: =(I60+I58)/I58 -> 2.3939183
B65: Debt-repayment schedule
B66: Term A
B67: Beginning-of-year (BOY) balance | E67: =E13 -> 3596.075 | F67: =E72 -> 3416.2713 | G67: =F72 -> 2953.6209 | H67: =G72 -> 2493.4106 | I67: =H72 -> 1893.9499
B68: Interest paid | E68: =E67*$F$13 -> 197.78413 | F68: =F67*$F$13 -> 187.89492 | G68: =G67*$F$13 -> 162.44915 | H68: =H67*$F$13 -> 137.13758 | I68: =I67*$F$13 -> 104.16724
B69: Principal repaid | E69: =IF(E67>E90, E90, E67) -> 216.23241 | F69: =IF(F67>F90, F90, F67) -> 462.65036 | G69: =IF(G67>G90, G90, G67) -> 460.2103 | H69: =IF(H67>H90, H90, H67) -> 599.46069 | I69: =IF(I67>I90, I90, I67) -> 656.78003
B70: Principal (5%) | E70: =$J$16*$E$13 -> 179.80375 | F70: =$J$16*$E$13 -> 179.80375 | G70: =$J$16*$E$13 -> 179.80375 | H70: =$J$16*$E$13 -> 179.80375 | I70: =$J$16*$E$13 -> 179.80375
B71: Sweep | E71: =IF(E69>288, E69-288, 0) -> 0 | F71: =IF(F69>288, F69-288, 0) -> 174.65036 | G71: =IF(G69>288, G69-288, 0) -> 172.2103 | H71: =IF(H69>288, H69-288, 0) -> 311.46069 | I71: =IF(I69>288, I69-288, 0) -> 368.78003
B72: End-of-year (EOY) balance | E72: =E67-(E70+E71) -> 3416.2713 | F72: =F67-F69 -> 2953.6209 | G72: =G67-G69 -> 2493.4106 | H72: =H67-H69 -> 1893.9499 | I72: =I67-I69 -> 1237.1699
B74: Term B
B75: BOY balance | E75: =E14 -> 1438.43 | F75: =E78 -> 1438.43 | G75: =F78 -> 1438.43 | H75: =G78 -> 1438.43 | I75: =H78 -> 1438.43
B76: Interest paid | E76: =E75*$F$14 -> 107.88225 | F76: =F75*$F$14 -> 107.88225 | G76: =G75*$F$14 -> 107.88225 | H76: =H75*$F$14 -> 107.88225 | I76: =I75*$F$14 -> 107.88225
B77: Principal repaid | E77: =E69-E90 -> 0 | F77: =F69-F90 -> 0 | G77: =G69-G90 -> 0 | H77: =H69-H90 -> 0 | I77: =I69-I90 -> 0
B78: EOY balance | E78: =E75-E77 -> 1438.43 | F78: =F75-F77 -> 1438.43 | G78: =G75-G77 -> 1438.43 | H78: =H75-H77 -> 1438.43 | I78: =I75-I77 -> 1438.43
B80: Cash available after Senior Debt & Unsecured Debt | E80: =E36-E68-E76 -> 376.36562 | F80: =F36-F68-F76 -> 629.66683 | G80: =G36-G68-G76 -> 637.7802 | H80: =H36-H68-H76 -> 787.64717 | I80: =I36-I68-I76 -> 857.44051
B82: Mezzanine
B83: BOY balance | E83: =E15 -> 2876.86 | F83: =E86 -> 2934.3972 | G83: =F86 -> 2993.0851 | H83: =G86 -> 3052.9468 | I83: =H86 -> 3114.0058
B84: Interest paid | E84: =E83*$F$15 -> 316.4546 | F84: =F83*$F$15 -> 322.78369 | G84: =G83*$F$15 -> 329.23937 | H84: =H83*$F$15 -> 335.82415 | I84: =I83*$F$15 -> 342.54064
B85: PIK | E85: =E83*$G$15 -> 57.5372 | F85: =F83*$G$15 -> 58.687944 | G85: =G83*$G$15 -> 59.861703 | H85: =H83*$G$15 -> 61.058937 | I85: =I83*$G$15 -> 62.280116
B86: EOY balance | E86: =E83+E85 -> 2934.3972 | F86: =F83+F85 -> 2993.0851 | G86: =G83+G85 -> 3052.9468 | H86: =H83+H85 -> 3114.0058 | I86: =I83+I85 -> 3176.2859
B88: Total cash interest paid | E88: =E68+E76+E84 -> 622.12098 | F88: =F68+F76+F84 -> 618.56086 | G88: =G68+G76+G84 -> 599.57076 | H88: =H68+H76+H84 -> 580.84399 | I88: =I68+I76+I84 -> 554.59013
B89: Interest tax shield | E89: =(E88+E85)*$D$8 -> 156.32138 | F89: =(F88+F85)*$D$8 -> 155.76723 | G89: =(G88+G85)*$D$8 -> 151.66947 | H89: =(H88+H85)*$D$8 -> 147.63767 | I89: =(I88+I85)*$D$8 -> 141.88016
B90: Cash flows available for debt repayment | E90: =E36-E88+E89 -> 216.23241 | F90: =F36-F88+F89 -> 462.65036 | G90: =G36-G88+G89 -> 460.2103 | H90: =H36-H88+H89 -> 599.46069 | I90: =I36-I88+I89 -> 656.78003
B91: Total debt outstanding | E91: =E72+E78+E86 -> 7789.0985 | F91: =F72+F78+F86 -> 7385.136 | G91: =G72+G78+G86 -> 6984.7874 | H91: =H72+H78+H86 -> 6446.3857 | I91: =I72+I78+I86 -> 5851.8858
B93: Beginning Cash | E93: =D9 -> 0 | F93: =E95 -> 0 | G93: =F95 -> 0 | H93: =G95 -> 0 | I93: =H95 -> 0
B94: Change in cash | E94: =E36-E88-E69+E89 -> 0 | F94: =F36-F88-F69+F89 -> 0 | G94: =G36-G88-G69+G89 -> 0 | H94: =H36-H88-H69+H89 -> 0 | I94: =I36-I88-I69+I89 -> 0
B95: Ending Cash | E95: =E93+E94 -> 0 | F95: =F93+F94 -> 0 | G95: =G93+G94 -> 0 | H95: =H93+H94 -> 0 | I95: =I93+I94 -> 0
B97: Step 4: Return Calculation
B98: Williams-Sonoma, Inc., LBO: Let’s Get Cooking
E99: Exit Year
E100: 1 | F100: 2 | G100: 3 | H100: 4 | I100: 5
B101: Exit Multiple (EV / LTM EBITDA) | D101: =I6 -> 7.5 | E101: =E29*$D$101 -> 10788.225 | F101: =F29*$D$101 -> 11105.1 | G101: =G29*$D$101 -> 11076.225 | H101: =H29*$D$101 -> 12844.575 | I101: =I29*$D$101 -> 13476.525
B103: Debt | E103: =E91 -> 7789.0985 | F103: =F91 -> 7385.136 | G103: =G91 -> 6984.7874 | H103: =H91 -> 6446.3857 | I103: =I91 -> 5851.8858
B104: Cash | E104: =E95 -> 0 | F104: =F95 -> 0 | G104: =G95 -> 0 | H104: =H95 -> 0 | I104: =I95 -> 0
B105: Equity Value | E105: =E101-E103+E104 -> 2999.1265 | F105: =F101-F103+F104 -> 3719.964 | G105: =G101-G103+G104 -> 4091.4376 | H105: =H101-H103+H104 -> 6398.1893 | I105: =I101-I103+I104 -> 7624.6392
B107: IRR | E107: =(E105/$E$16)^(1/E100)-1 -> 0.0425 | F107: =(F105/$E$16)^(1/F100)-1 -> 0.1371297 | G107: =(G105/$E$16)^(1/G100)-1 -> 0.12456803 | H107: =(H105/$E$16)^(1/H100)-1 -> 0.2211938 | I107: =(I105/$E$16)^(1/I100)-1 -> 0.21523457
B108: MOIC (Multiple on invested Capital) | E108: =E105/$E$16 -> 1.0425 | F108: =F105/$E$16 -> 1.293064 | G108: =G105/$E$16 -> 1.4221886 | H108: =H105/$E$16 -> 2.2240183 | I108: =I105/$E$16 -> 2.6503338
B111: Cavalier Capital
B112: Equity stake of mezzanine investors | I112: 0.05
B113: Equity value to mezzanine investors | I113: =+I105*I112 -> 381.23196
B114: Cash flows for mezzanine investors | D114: =-E15 -> -2876.86 | E114: =E84 -> 316.4546 | F114: =F84 -> 322.78369 | G114: =G84 -> 329.23937 | H114: =H84 -> 335.82415 | I114: =I84+MIN(I86,I101-I78-I72)+I113 -> 3900.0585
B115: Mezzanine internal rate of return (IRR) | D115: =IRR(D114:I114) -> 0.1490239
B116: Mezzanine cash on cash | D116: =SUM(E114:I114)/-D114 -> 1.8090419
B118: Jefferson Capital Management
B119: Cash flows for equity investors | D119: =-E16 -> -2876.86 | E119: 0 | F119: 0 | G119: 0 | H119: 0 | I119: =I105-I113 -> 7243.4073
B120: Equity IRR | D120: =IRR(D119:I119) -> 0.20283162
B121: Equity cash on cash | D121: =SUM(E119:I119)/-D119 -> 2.5178171
B124: Step 5: Sensitivity Analysis
F126: Cavalier Capital
C127: IRR of Equity Investment
...

Sheet LBO Model- OPTIMAL CASE
A1: Luke Buddie, Gennaro Di Mauro, Peter Spira, Caden Carney
B2: Step 1: Outline everything you know
B3: Williams-Sonoma, Inc., LBO: Let’s Get Cooking
B4: Assumptions
B6: 2024 EBITDA | D6: ='Ex 10 Projections'!E18 -> 1438.43 | E6: Exhibit 10 | H6: Exit multiple | I6: =D12 -> 7.5 | L6: Term A | M6: =E13 -> 4315.29
B7: SOFR | D7: 0.03 | H7: Number of shares outstanding (in millions) | I7: ='Ex 11 Comps'!I16 -> 64.2 | J7: Exhibit 11 | L7: Term B | M7: =E14 -> 2157.645
B8: Tax rate | D8: 0.23 | E8: Exhibit 10 | H8: Current enterprise value | I8: =('Ex 11 Comps'!I16*'Ex 11 Comps'!J16)+'Ex 11 Comps'!K16 -> 8758.648 | J8: Equity Value + Debt Value | L8: Sub Debt | M8: =E15 -> 1438.43
B9: Opening Balance Cash | D9: 0 | E9: Exhibit 9 - Case | L9: Equity | M9: =E16 -> 2876.86
L10: Bid | M10: =SUM(M6:M9) -> 10788.225
B11: Financing Package | E11: Amount | F11: Cash Interest | G11: PIK | J11: SOFR +
B12: Purchase multiple | D12: =SUM(D13:D16) -> 7.5 | E12: =D6*D12 -> 10788.225 | L12: EBITDA | M12: =E30 -> 1438.43
B13: Term A | D13: 3 | E13: =D13*$D$6 -> 4315.29 | F13: =D7+J13 -> 0.055 | J13: 0.025 | L13: Multiple: | M13: =M10/M12 -> 7.5
B14: Term B | D14: 1.5 | E14: =D14*$D$6 -> 2157.645 | F14: =D7+J14 -> 0.075 | J14: 0.045
B15: Mezzanine (Cavalier Capital) | D15: 1 | E15: =D15*$D$6 -> 1438.43 | F15: 0.11 | G15: 0.02 | J15: Minimum Priciple
B16: Equity investment (Jeffereson Capital Management) | D16: 2 | E16: =E12-E13-E14-E15 -> 2876.86 | J16: 0.05
B19: Step 2: How/Who are you going to pay down your debt with your free cash flow?
B20: Williams-Sonoma, Inc., LBO: Let’s Get Cooking
B21: Debt-Repayment Schedule | K21: Target Leverage
K22: Debt/EBITDA: 4-6x
D23: 2023 | E23: 2024 | F23: 2025 | G23: 2026 | H23: 2027 | I23: 2028
B24: ='Ex 10 Projections'!B11 -> Total revenue | D24: ='Ex 10 Projections'!D11 -> 8674.42 | E24: ='Ex 10 Projections'!E11 -> 8471 | F24: ='Ex 10 Projections'!F11 -> 8553 | G24: ='Ex 10 Projections'!G11 -> 8862.29 | H24: ='Ex 10 Projections'!H11 -> 9181.33 | I24: ='Ex 10 Projections'!I11 -> 9582.61
B25: ='Ex 10 Projections'!B12 -> Cost of goods sold | D25: ='Ex 10 Projections'!D12 -> 4996.68 | E25: ='Ex 10 Projections'!E12 -> 5067.8 | F25: ='Ex 10 Projections'!F12 -> 5082.1 | G25: ='Ex 10 Projections'!G12 -> 5241.16 | H25: ='Ex 10 Projections'!H12 -> 5407.8 | I25: ='Ex 10 Projections'!I12 -> 5605.83
B26: ='Ex 10 Projections'!B13 -> Gross profit | D26: =D24-D25 -> 3677.74 | E26: =E24-E25 -> 3403.2 | F26: =F24-F25 -> 3470.9 | G26: =G24-G25 -> 3621.13 | H26: =H24-H25 -> 3773.53 | I26: =I24-I25 -> 3976.78
B27: ='Ex 10 Projections'!B14 -> Selling, general, and administrative expenses | D27: ='Ex 10 Projections'!D14 -> 2179.31 | E27: ='Ex 10 Projections'!E14 -> 2189.6 | F27: ='Ex 10 Projections'!F14 -> 2223.7 | G27: ='Ex 10 Projections'!G14 -> 2395.05 | H27: ='Ex 10 Projections'!H14 -> 2313.43 | I27: ='Ex 10 Projections'!I14 -> 2443.78
B28: ='Ex 10 Projections'!B17 -> Depreciation and amortization | D28: ='Ex 10 Projections'!D17 -> 214.2 | E28: ='Ex 10 Projections'!E17 -> 224.83 | F28: ='Ex 10 Projections'!F17 -> 233.48 | G28: ='Ex 10 Projections'!G17 -> 250.75 | H28: ='Ex 10 Projections'!H17 -> 252.51 | I28: ='Ex 10 Projections'!I17 -> 263.87
B29: ='Ex 10 Projections'!B18 -> EBITDA | D29: =(D26-D27+D28) -> 1712.63 | E29: =(E26-E27+E28) -> 1438.43 | F29: =(F26-F27+F28) -> 1480.68 | G29: =(G26-G27+G28) -> 1476.83 | H29: =(H26-H27+H28) -> 1712.61 | I29: =(I26-I27+I28) -> 1796.87
B30: Haircut to EBITDA (difference from expected EBITDA vs. realitstic) | C30: 0 | D30: =D29*(1+$C$30) -> 1712.63 | E30: =E29*(1+$C$30) -> 1438.43 | F30: =F29*(1+$C$30) -> 1480.68 | G30: =G29*(1+$C$30) -> 1476.83 | H30: =H29*(1+$C$30) -> 1712.61 | I30: =I29*(1+$C$30) -> 1796.87
B32: ='Ex 10 Projections'!B15 -> Operating income (EBIT) | D32: =D30-D28 -> 1498.43 | E32: =E30-E28 -> 1213.6 | F32: =F30-F28 -> 1247.2 | G32: =G30-G28 -> 1226.08 | H32: =H30-H28 -> 1460.1 | I32: =I30-I28 -> 1533
B33: ='Ex 10 Projections'!B22 -> CAPEX | D33: ='Ex 10 Projections'!D22 -> 354.1 | E33: ='Ex 10 Projections'!E22 -> 249.4 | F33: ='Ex 10 Projections'!F22 -> 262.31 | G33: ='Ex 10 Projections'!G22 -> 263.81 | H33: ='Ex 10 Projections'!H22 -> 320.49 | I33: ='Ex 10 Projections'!I22 -> 345.07
B34: ='Ex 10 Projections'!B23 -> Change in net working capital (NWC) | D34: ='Ex 10 Projections'!D23 -> -152.6 | E34: ='Ex 10 Projections'!E23 -> 227.87 | F34: ='Ex 10 Projections'!F23 -> 6.07 | G34: ='Ex 10 Projections'!G23 -> 22.91 | H34: ='Ex 10 Projections'!H23 -> 23.63 | I34: ='Ex 10 Projections'!I23 -> 29.72
B36: FCF | E36: =E32*(1-$D$8)+E28-E33-E34 -> 682.032 | F36: =F32*(1-$D$8)+F28-F33-F34 -> 925.444 | G36: =G32*(1-$D$8)+G28-G33-G34 -> 908.1116 | H36: =H32*(1-$D$8)+H28-H33-H34 -> 1032.667 | I36: =I32*(1-$D$8)+I28-I33-I34 -> 1069.49
B37: Beginning Balance | E37: =E13 -> 4315.29 | F37: =E37-E38 -> 4099.5255 | G37: =F37-F38 -> 3883.761 | H37: =G37-G38 -> 3667.9965 | I37: =H37-H38 -> 3452.232
B38: Term A Principal | E38: =$J$16*$E$37 -> 215.7645 | F38: =$J$16*$E$37 -> 215.7645 | G38: =$J$16*$E$37 -> 215.7645 | H38: =$J$16*$E$37 -> 215.7645 | I38: =$J$16*$E$37 -> 215.7645
B39: Interest | E39: =$F$13*E37 -> 237.34095 | F39: =$F$13*F37 -> 225.4739 | G39: =$F$13*G37 -> 213.60685 | H39: =$F$13*H37 -> 201.73981 | I39: =$F$13*I37 -> 189.87276
B41: Total Debt | E41: =E38+E39 -> 453.10545 | F41: =F38+F39 -> 441.2384 | G41: =G38+G39 -> 429.37135 | H41: =H38+H39 -> 417.50431 | I41: =I38+I39 -> 405.63726
B42: Tax shield | E42: =E39*$D$8 -> 54.588419 | F42: =F39*$D$8 -> 51.858998 | G42: =G39*$D$8 -> 49.129577 | H42: =H39*$D$8 -> 46.400156 | I42: =I39*$D$8 -> 43.670735
B43: Excess Cash Flow | E43: =E36-E41+E42 -> 283.51497 | F43: =F36-F41+F42 -> 536.0646 | G43: =G36-G41+G42 -> 527.86982 | H43: =H36-H41+H42 -> 661.56285 | I43: =I36-I41+I42 -> 707.52347
B44: FCC | E44: =(E41+E43)/E41 -> 1.6257152 | F44: =(F41+F43)/F41 -> 2.2149092 | G44: =(G41+G43)/G41 -> 2.2294016 | H44: =(H41+H43)/H41 -> 2.5845653 | I44: =(I41+I43)/I41 -> 2.744227
B46: Term B
B47: FCF | E47: =E43 -> 283.51497 | F47: =F43 -> 536.0646 | G47: =G43 -> 527.86982 | H47: =H43 -> 661.56285 | I47: =I43 -> 707.52347
B48: No principal
B49: Interest | E49: =$F$14*$E$14 -> 161.82337 | F49: =$F$14*$E$14 -> 161.82337 | G49: =$F$14*$E$14 -> 161.82337 | H49: =$F$14*$E$14 -> 161.82337 | I49: =$F$14*$E$14 -> 161.82337
B51: Total Debt | E51: =E49 -> 161.82337 | F51: =F49 -> 161.82337 | G51: =G49 -> 161.82337 | H51: =H49 -> 161.82337 | I51: =I49 -> 161.82337
B52: Tax Shield | E52: =E49*$D$8 -> 37.219376 | F52: =F49*$D$8 -> 37.219376 | G52: =G49*$D$8 -> 37.219376 | H52: =H49*$D$8 -> 37.219376 | I52: =I49*$D$8 -> 37.219376
B53: Excess | E53: =E47-E51+E52 -> 158.91097 | F53: =F47-F51+F52 -> 411.4606 | G53: =G47-G51+G52 -> 403.26582 | H53: =H47-H51+H52 -> 536.95885 | I53: =I47-I51+I52 -> 582.91948
B54: FCC | E54: =(E51+E53)/E51 -> 1.9820026 | F54: =(F51+F53)/F51 -> 3.5426524 | G54: =(G51+G53)/G51 -> 3.4920122 | H54: =(H51+H53)/H51 -> 4.3181785 | I54: =(I51+I53)/I51 -> 4.6021958
B56: Mezzanine | E56: =E53 -> 158.91097 | F56: =F53 -> 411.4606 | G56: =G53 -> 403.26582 | H56: =H53 -> 536.95885 | I56: =I53 -> 582.91948
B57: Interest | E57: =$F$15*$E$15 -> 158.2273 | F57: =$F$15*$E$15 -> 158.2273 | G57: =$F$15*$E$15 -> 158.2273 | H57: =$F$15*$E$15 -> 158.2273 | I57: =$F$15*$E$15 -> 158.2273
B58: Total Debt | E58: =E57 -> 158.2273 | F58: =F57 -> 158.2273 | G58: =G57 -> 158.2273 | H58: =H57 -> 158.2273 | I58: =I57 -> 158.2273
B59: Tax Shield | E59: =E58*$D$8 -> 36.392279 | F59: =F58*$D$8 -> 36.392279 | G59: =G58*$D$8 -> 36.392279 | H59: =H58*$D$8 -> 36.392279 | I59: =I58*$D$8 -> 36.392279
B60: Excess | E60: =E56-E58+E59 -> 37.075949 | F60: =F56-F58+F59 -> 289.62558 | G60: =G56-G58+G59 -> 281.4308 | H60: =H56-H58+H59 -> 415.12383 | I60: =I56-I58+I59 -> 461.08446
B61: FCC | E61: =(E60+E58)/E58 -> 1.2343208 | F61: =(F60+F58)/F58 -> 2.83044 | G61: =(G60+G58)/G58 -> 2.7786488 | H61: =(H60+H58)/H58 -> 3.6235917 | I61: =(I60+I58)/I58 -> 3.9140639
B65: Debt-repayment schedule
B66: Term A
B67: Beginning-of-year (BOY) balance | E67: =E13 -> 4315.29 | F67: =E72 -> 4099.5255 | G67: =F72 -> 3589.823 | H67: =G72 -> 3078.2175 | I67: =H72 -> 2422.7875
B68: Interest paid | E68: =E67*$F$13 -> 237.34095 | F68: =F67*$F$13 -> 225.4739 | G68: =G67*$F$13 -> 197.44027 | H68: =H67*$F$13 -> 169.30196 | I68: =I67*$F$13 -> 133.25331
B69: Principal repaid | E69: =IF(E67>E90, E90, E67) -> 259.45723 | F69: =IF(F67>F90, F90, F67) -> 509.70249 | G69: =IF(G67>G90, G90, G67) -> 511.60554 | H69: =IF(H67>H90, H90, H67) -> 655.42997 | I69: =IF(I67>I90, I90, I67) -> 717.56502
B70: Principal (5%) | E70: =$J$16*$E$13 -> 215.7645 | F70: =$J$16*$E$13 -> 215.7645 | G70: =$J$16*$E$13 -> 215.7645 | H70: =$J$16*$E$13 -> 215.7645 | I70: =$J$16*$E$13 -> 215.7645
B71: Sweep | E71: =IF(E69>288, E69-288, 0) -> 0 | F71: =IF(F69>288, F69-288, 0) -> 221.70249 | G71: =IF(G69>288, G69-288, 0) -> 223.60554 | H71: =IF(H69>288, H69-288, 0) -> 367.42997 | I71: =IF(I69>288, I69-288, 0) -> 429.56502
B72: End-of-year (EOY) balance | E72: =E67-(E70+E71) -> 4099.5255 | F72: =F67-F69 -> 3589.823 | G72: =G67-G69 -> 3078.2175 | H72: =H67-H69 -> 2422.7875 | I72: =I67-I69 -> 1705.2225
B74: Term B
B75: BOY balance | E75: =E14 -> 2157.645 | F75: =E78 -> 2157.645 | G75: =F78 -> 2157.645 | H75: =G78 -> 2157.645 | I75: =H78 -> 2157.645
B76: Interest paid | E76: =E75*$F$14 -> 161.82337 | F76: =F75*$F$14 -> 161.82337 | G76: =G75*$F$14 -> 161.82337 | H76: =H75*$F$14 -> 161.82337 | I76: =I75*$F$14 -> 161.82337
B77: Principal repaid | E77: =E69-E90 -> 0 | F77: =F69-F90 -> 0 | G77: =G69-G90 -> 0 | H77: =H69-H90 -> 0 | I77: =I69-I90 -> 0
B78: EOY balance | E78: =E75-E77 -> 2157.645 | F78: =F75-F77 -> 2157.645 | G78: =G75-G77 -> 2157.645 | H78: =H75-H77 -> 2157.645 | I78: =I75-I77 -> 2157.645
B80: Cash available after Senior Debt & Unsecured Debt | E80: =E36-E68-E76 -> 282.86767 | F80: =F36-F68-F76 -> 538.14672 | G80: =G36-G68-G76 -> 548.84796 | H80: =H36-H68-H76 -> 701.54166 | I80: =I36-I68-I76 -> 774.41331
B82: Mezzanine
B83: BOY balance | E83: =E15 -> 1438.43 | F83: =E86 -> 1467.1986 | G83: =F86 -> 1496.5426 | H83: =G86 -> 1526.4734 | I83: =H86 -> 1557.0029
B84: Interest paid | E84: =E83*$F$15 -> 158.2273 | F84: =F83*$F$15 -> 161.39185 | G84: =G83*$F$15 -> 164.61968 | H84: =H83*$F$15 -> 167.91208 | I84: =I83*$F$15 -> 171.27032
B85: PIK | E85: =E83*$G$15 -> 28.7686 | F85: =F83*$G$15 -> 29.343972 | G85: =G83*$G$15 -> 29.930851 | H85: =H83*$G$15 -> 30.529468 | I85: =I83*$G$15 -> 31.140058
B86: EOY balance | E86: =E83+E85 -> 1467.1986 | F86: =F83+F85 -> 1496.5426 | G86: =G83+G85 -> 1526.4734 | H86: =H83+H85 -> 1557.0029 | I86: =I83+I85 -> 1588.1429
B88: Total cash interest paid | E88: =E68+E76+E84 -> 557.39162 | F88: =F68+F76+F84 -> 548.68912 | G88: =G68+G76+G84 -> 523.88332 | H88: =H68+H76+H84 -> 499.03741 | I88: =I68+I76+I84 -> 466.34701
B89: Interest tax shield | E89: =(E88+E85)*$D$8 -> 134.81685 | F89: =(F88+F85)*$D$8 -> 132.94761 | G89: =(G88+G85)*$D$8 -> 127.37726 | H89: =(H88+H85)*$D$8 -> 121.80038 | I89: =(I88+I85)*$D$8 -> 114.42202
B90: Cash flows available for debt repayment | E90: =E36-E88+E89 -> 259.45723 | F90: =F36-F88+F89 -> 509.70249 | G90: =G36-G88+G89 -> 511.60554 | H90: =H36-H88+H89 -> 655.42997 | I90: =I36-I88+I89 -> 717.56502
B91: Total debt outstanding | E91: =E72+E78+E86 -> 7724.3691 | F91: =F72+F78+F86 -> 7244.0106 | G91: =G72+G78+G86 -> 6762.3359 | H91: =H72+H78+H86 -> 6137.4354 | I91: =I72+I78+I86 -> 5451.0104
B93: Beginning Cash | E93: =D9 -> 0 | F93: =E95 -> 0 | G93: =F95 -> 0 | H93: =G95 -> 0 | I93: =H95 -> 0
B94: Change in cash | E94: =E36-E88-E69+E89 -> 0 | F94: =F36-F88-F69+F89 -> 0 | G94: =G36-G88-G69+G89 -> 0 | H94: =H36-H88-H69+H89 -> 0 | I94: =I36-I88-I69+I89 -> 0
B95: Ending Cash | E95: =E93+E94 -> 0 | F95: =F93+F94 -> 0 | G95: =G93+G94 -> 0 | H95: =H93+H94 -> 0 | I95: =I93+I94 -> 0
B97: Step 4: Return Calculation
B98: Williams-Sonoma, Inc., LBO: Let’s Get Cooking
E99: Exit Year
E100: 1 | F100: 2 | G100: 3 | H100: 4 | I100: 5
B101: Exit Multiple (EV / LTM EBITDA) | D101: =I6 -> 7.5 | E101: =E29*$D$101 -> 10788.225 | F101: =F29*$D$101 -> 11105.1 | G101: =G29*$D$101 -> 11076.225 | H101: =H29*$D$101 -> 12844.575 | I101: =I29*$D$101 -> 13476.525
B103: Debt | E103: =E91 -> 7724.3691 | F103: =F91 -> 7244.0106 | G103: =G91 -> 6762.3359 | H103: =H91 -> 6137.4354 | I103: =I91 -> 5451.0104
B104: Cash | E104: =E95 -> 0 | F104: =F95 -> 0 | G104: =G95 -> 0 | H104: =H95 -> 0 | I104: =I95 -> 0
B105: Equity Value | E105: =E101-E103+E104 -> 3063.8559 | F105: =F101-F103+F104 -> 3861.0894 | G105: =G101-G103+G104 -> 4313.8891 | H105: =H101-H103+H104 -> 6707.1396 | I105: =I101-I103+I104 -> 8025.5146
B107: IRR | E107: =(E105/$E$16)^(1/E100)-1 -> 0.065 | F107: =(F105/$E$16)^(1/F100)-1 -> 0.15849874 | G107: =(G105/$E$16)^(1/G100)-1 -> 0.14459036 | H107: =(H105/$E$16)^(1/H100)-1 -> 0.23567612 | I107: =(I105/$E$16)^(1/I100)-1 -> 0.22775251
B108: MOIC (Multiple on invested Capital) | E108: =E105/$E$16 -> 1.065 | F108: =F105/$E$16 -> 1.3421193 | G108: =G105/$E$16 -> 1.499513 | H108: =H105/$E$16 -> 2.3314098 | I108: =I105/$E$16 -> 2.7896785
B111: Cavalier Capital
B112: Equity stake of mezzanine investors | I112: 0.05
B113: Equity value to mezzanine investors | I113: =+I105*I112 -> 401.27573
B114: Cash flows for mezzanine investors | D114: =-E15 -> -1438.43 | E114: =E84 -> 158.2273 | F114: =F84 -> 161.39185 | G114: =G84 -> 164.61968 | H114: =H84 -> 167.91208 | I114: =I84+MIN(I86,I101-I78-I72)+I113 -> 2160.689
B115: Mezzanine internal rate of return (IRR) | D115: =IRR(D114:I114) -> 0.16855567
B116: Mezzanine cash on cash | D116: =SUM(E114:I114)/-D114 -> 1.9554931
B118: Jefferson Capital Management
B119: Cash flows for equity investors | D119: =-E16 -> -2876.86 | E119: 0 | F119: 0 | G119: 0 | H119: 0 | I119: =I105-I113 -> 7624.2388
B120: Equity IRR | D120: =IRR(D119:I119) -> 0.2152218
B121: Equity cash on cash | D121: =SUM(E119:I119)/-D119 -> 2.6501946
B124: Step 5: Sensitivity Analysis
F126: Cavalier Capital
...

Sheet LBO Model- 4x Debt A
A1: Luke Buddie, Gennaro Di Mauro, Peter Spira, Caden Carney
B2: Step 1: Outline everything you know
B3: Williams-Sonoma, Inc., LBO: Let’s Get Cooking
B4: Assumptions
B6: 2024 EBITDA | D6: ='Ex 10 Projections'!E18 -> 1438.43 | E6: Exhibit 10 | H6: Exit multiple | I6: =D12 -> 9
B7: SOFR | D7: 0.03 | H7: Number of shares outstanding (in millions) | I7: ='Ex 11 Comps'!I16 -> 64.2 | J7: Exhibit 11
B8: Tax rate | D8: 0.23 | E8: Exhibit 10 | H8: Current enterprise value | I8: =('Ex 11 Comps'!I16*'Ex 11 Comps'!J16)+'Ex 11 Comps'!K16 -> 8758.648 | J8: Equity Value + Debt Value
B9: Opening Balance Cash | D9: 0 | E9: Exhibit 9 - Case
B11: Financing Package | E11: Amount | F11: Cash Interest | G11: PIK | H11: Target L:everage | J11: SOFR +
B12: Purchase multiple | D12: =SUM(D13:D16) -> 9 | E12: =D6*D12 -> 12945.87
B13: Term A | D13: 4 | E13: =D13*$D$6 -> 5753.72 | F13: =D7+J13 -> 0.055 | H13: =(E13+E14)/E29 -> 5 | J13: 0.025
B14: Term B | D14: 1 | E14: =D14*$D$6 -> 1438.43 | F14: =D7+J14 -> 0.075 | J14: 0.045
B15: Mezzanine (Cavalier Capital) | D15: 2 | E15: =D15*$D$6 -> 2876.86 | F15: 0.11 | G15: 0.02 | J15: Minimum Priciple
B16: Equity investment (Jeffereson Capital Management) | D16: 2 | E16: =E12-E13-E14-E15 -> 2876.86 | J16: 0.05
B19: Step 2: How/Who are you going to pay down your debt with your free cash flow?
B20: Williams-Sonoma, Inc., LBO: Let’s Get Cooking
B21: Debt-Repayment Schedule | K21: Target Leverage
K22: Debt/EBITDA: 4-6x
D23: 2023 | E23: 2024 | F23: 2025 | G23: 2026 | H23: 2027 | I23: 2028
B24: ='Ex 10 Projections'!B11 -> Total revenue | D24: ='Ex 10 Projections'!D11 -> 8674.42 | E24: ='Ex 10 Projections'!E11 -> 8471 | F24: ='Ex 10 Projections'!F11 -> 8553 | G24: ='Ex 10 Projections'!G11 -> 8862.29 | H24: ='Ex 10 Projections'!H11 -> 9181.33 | I24: ='Ex 10 Projections'!I11 -> 9582.61
B25: ='Ex 10 Projections'!B12 -> Cost of goods sold | D25: ='Ex 10 Projections'!D12 -> 4996.68 | E25: ='Ex 10 Projections'!E12 -> 5067.8 | F25: ='Ex 10 Projections'!F12 -> 5082.1 | G25: ='Ex 10 Projections'!G12 -> 5241.16 | H25: ='Ex 10 Projections'!H12 -> 5407.8 | I25: ='Ex 10 Projections'!I12 -> 5605.83
B26: ='Ex 10 Projections'!B13 -> Gross profit | D26: =D24-D25 -> 3677.74 | E26: =E24-E25 -> 3403.2 | F26: =F24-F25 -> 3470.9 | G26: =G24-G25 -> 3621.13 | H26: =H24-H25 -> 3773.53 | I26: =I24-I25 -> 3976.78
B27: ='Ex 10 Projections'!B14 -> Selling, general, and administrative expenses | D27: ='Ex 10 Projections'!D14 -> 2179.31 | E27: ='Ex 10 Projections'!E14 -> 2189.6 | F27: ='Ex 10 Projections'!F14 -> 2223.7 | G27: ='Ex 10 Projections'!G14 -> 2395.05 | H27: ='Ex 10 Projections'!H14 -> 2313.43 | I27: ='Ex 10 Projections'!I14 -> 2443.78
B28: ='Ex 10 Projections'!B17 -> Depreciation and amortization | D28: ='Ex 10 Projections'!D17 -> 214.2 | E28: ='Ex 10 Projections'!E17 -> 224.83 | F28: ='Ex 10 Projections'!F17 -> 233.48 | G28: ='Ex 10 Projections'!G17 -> 250.75 | H28: ='Ex 10 Projections'!H17 -> 252.51 | I28: ='Ex 10 Projections'!I17 -> 263.87
B29: ='Ex 10 Projections'!B18 -> EBITDA | D29: =(D26-D27+D28) -> 1712.63 | E29: =(E26-E27+E28) -> 1438.43 | F29: =(F26-F27+F28) -> 1480.68 | G29: =(G26-G27+G28) -> 1476.83 | H29: =(H26-H27+H28) -> 1712.61 | I29: =(I26-I27+I28) -> 1796.87
B30: Haircut to EBITDA (difference from expected EBITDA vs. realitstic) | C30: 0 | D30: =D29*(1+$C$30) -> 1712.63 | E30: =E29*(1+$C$30) -> 1438.43 | F30: =F29*(1+$C$30) -> 1480.68 | G30: =G29*(1+$C$30) -> 1476.83 | H30: =H29*(1+$C$30) -> 1712.61 | I30: =I29*(1+$C$30) -> 1796.87
B32: ='Ex 10 Projections'!B15 -> Operating income (EBIT) | D32: =D30-D28 -> 1498.43 | E32: =E30-E28 -> 1213.6 | F32: =F30-F28 -> 1247.2 | G32: =G30-G28 -> 1226.08 | H32: =H30-H28 -> 1460.1 | I32: =I30-I28 -> 1533
B33: ='Ex 10 Projections'!B22 -> CAPEX | D33: ='Ex 10 Projections'!D22 -> 354.1 | E33: ='Ex 10 Projections'!E22 -> 249.4 | F33: ='Ex 10 Projections'!F22 -> 262.31 | G33: ='Ex 10 Projections'!G22 -> 263.81 | H33: ='Ex 10 Projections'!H22 -> 320.49 | I33: ='Ex 10 Projections'!I22 -> 345.07
B34: ='Ex 10 Projections'!B23 -> Change in net working capital (NWC) | D34: ='Ex 10 Projections'!D23 -> -152.6 | E34: ='Ex 10 Projections'!E23 -> 227.87 | F34: ='Ex 10 Projections'!F23 -> 6.07 | G34: ='Ex 10 Projections'!G23 -> 22.91 | H34: ='Ex 10 Projections'!H23 -> 23.63 | I34: ='Ex 10 Projections'!I23 -> 29.72
B36: FCF | E36: =E32*(1-$D$8)+E28-E33-E34 -> 682.032 | F36: =F32*(1-$D$8)+F28-F33-F34 -> 925.444 | G36: =G32*(1-$D$8)+G28-G33-G34 -> 908.1116 | H36: =H32*(1-$D$8)+H28-H33-H34 -> 1032.667 | I36: =I32*(1-$D$8)+I28-I33-I34 -> 1069.49
B37: Beginning Balance | E37: =E13 -> 5753.72 | F37: =E37-E38 -> 5466.034 | G37: =F37-F38 -> 5178.348 | H37: =G37-G38 -> 4890.662 | I37: =H37-H38 -> 4602.976
B38: Team A FCC (4x, 3x, 2x) Principal | E38: =$J$16*$E$37 -> 287.686 | F38: =$J$16*$E$37 -> 287.686 | G38: =$J$16*$E$37 -> 287.686 | H38: =$J$16*$E$37 -> 287.686 | I38: =$J$16*$E$37 -> 287.686
B39: Interest | E39: =$F$13*E37 -> 316.4546 | F39: =$F$13*F37 -> 300.63187 | G39: =$F$13*G37 -> 284.80914 | H39: =$F$13*H37 -> 268.98641 | I39: =$F$13*I37 -> 253.16368
B41: Total Debt | E41: =E38+E39 -> 604.1406 | F41: =F38+F39 -> 588.31787 | G41: =G38+G39 -> 572.49514 | H41: =H38+H39 -> 556.67241 | I41: =I38+I39 -> 540.84968
B42: Tax shield | E42: =E39*$D$8 -> 72.784558 | F42: =F39*$D$8 -> 69.14533 | G42: =G39*$D$8 -> 65.506102 | H42: =H39*$D$8 -> 61.866874 | I42: =I39*$D$8 -> 58.227646
B43: Excess Cash Flow | E43: =E36-E41+E42 -> 150.67596 | F43: =F36-F41+F42 -> 406.27146 | G43: =G36-G41+G42 -> 401.12256 | H43: =H36-H41+H42 -> 537.86146 | I43: =I36-I41+I42 -> 586.86797
B44: FCC | E44: =(E41+E43)/E41 -> 1.2494054 | F44: =(F41+F43)/F41 -> 1.6905645 | G44: =(G41+G43)/G41 -> 1.7006567 | H44: =(H41+H43)/H41 -> 1.9662082 | I44: =(I41+I43)/I41 -> 2.0850852
B46: Term B
B47: FCF | E47: =E43 -> 150.67596 | F47: =F43 -> 406.27146 | G47: =G43 -> 401.12256 | H47: =H43 -> 537.86146 | I47: =I43 -> 586.86797
B48: No principal
B49: Interest | E49: =$F$14*$E$14 -> 107.88225 | F49: =$F$14*$E$14 -> 107.88225 | G49: =$F$14*$E$14 -> 107.88225 | H49: =$F$14*$E$14 -> 107.88225 | I49: =$F$14*$E$14 -> 107.88225
B51: Total Debt | E51: =E49 -> 107.88225 | F51: =F49 -> 107.88225 | G51: =G49 -> 107.88225 | H51: =H49 -> 107.88225 | I51: =I49 -> 107.88225
B52: Tax Shield | E52: =E49*$D$8 -> 24.812918 | F52: =F49*$D$8 -> 24.812918 | G52: =G49*$D$8 -> 24.812918 | H52: =H49*$D$8 -> 24.812918 | I52: =I49*$D$8 -> 24.812918
B53: Excess | E53: =E47-E51+E52 -> 67.606625 | F53: =F47-F51+F52 -> 323.20213 | G53: =G47-G51+G52 -> 318.05323 | H53: =H47-H51+H52 -> 454.79213 | I53: =I47-I51+I52 -> 503.79863
B54: FCC | E54: =(E51+E53)/E51 -> 1.6266705 | F54: =(F51+F53)/F51 -> 3.9958786 | G54: =(G51+G53)/G51 -> 3.9481516 | H54: =(H51+H53)/H51 -> 5.2156345 | I54: =(I51+I53)/I51 -> 5.6698936
B56: Mezzanine | E56: =E53 -> 67.606625 | F56: =F53 -> 323.20213 | G56: =G53 -> 318.05323 | H56: =H53 -> 454.79213 | I56: =I53 -> 503.79863
B57: Interest | E57: =$F$15*$E$15 -> 316.4546 | F57: =$F$15*$E$15 -> 316.4546 | G57: =$F$15*$E$15 -> 316.4546 | H57: =$F$15*$E$15 -> 316.4546 | I57: =$F$15*$E$15 -> 316.4546
B58: Total Debt | E58: =E57 -> 316.4546 | F58: =F57 -> 316.4546 | G58: =G57 -> 316.4546 | H58: =H57 -> 316.4546 | I58: =I57 -> 316.4546
B59: Tax Shield | E59: =E58*$D$8 -> 72.784558 | F59: =F58*$D$8 -> 72.784558 | G59: =G58*$D$8 -> 72.784558 | H59: =H58*$D$8 -> 72.784558 | I59: =I58*$D$8 -> 72.784558
B60: Excess | E60: =E56-E58+E59 -> -176.06342 | F60: =F56-F58+F59 -> 79.532086 | G60: =G56-G58+G59 -> 74.383188 | H60: =H56-H58+H59 -> 211.12209 | I60: =I56-I58+I59 -> 260.12859
B61: FCC | E61: =(E60+E58)/E58 -> 0.44363768 | F61: =(F60+F58)/F58 -> 1.2513223 | G61: =(G60+G58)/G58 -> 1.2350517 | H61: =(H60+H58)/H58 -> 1.6671481 | I61: =(I60+I58)/I58 -> 1.8220092
B65: Debt-repayment schedule
B66: Term A
B67: Beginning-of-year (BOY) balance | E67: =E13 -> 5753.72 | F67: =E72 -> 5466.034 | G67: =F72 -> 5090.1911 | H67: =G72 -> 4720.4645 | I67: =H72 -> 4215.3196
B68: Interest paid | E68: =E67*$F$13 -> 316.4546 | F68: =F67*$F$13 -> 300.63187 | G68: =G67*$F$13 -> 279.96051 | H68: =H67*$F$13 -> 259.62555 | I68: =I67*$F$13 -> 231.84258
B69: Principal repaid | E69: =IF(E67>E90, E90, E67) -> 124.85614 | F69: =IF(F67>F90, F90, F67) -> 375.84291 | G69: =IF(G67>G90, G90, G67) -> 369.72655 | H69: =IF(H67>H90, H90, H67) -> 505.14495 | I69: =IF(I67>I90, I90, I67) -> 558.47002
B70: Principal (5%) | E70: =$J$16*$E$13 -> 287.686 | F70: =$J$16*$E$13 -> 287.686 | G70: =$J$16*$E$13 -> 287.686 | H70: =$J$16*$E$13 -> 287.686 | I70: =$J$16*$E$13 -> 287.686
B71: Sweep | E71: =IF(E69>288, E69-288, 0) -> 0 | F71: =IF(F69>288, F69-288, 0) -> 87.842912 | G71: =IF(G69>288, G69-288, 0) -> 81.726555 | H71: =IF(H69>288, H69-288, 0) -> 217.14495 | I71: =IF(I69>288, I69-288, 0) -> 270.47002
B72: End-of-year (EOY) balance | E72: =E67-(E70+E71) -> 5466.034 | F72: =F67-F69 -> 5090.1911 | G72: =G67-G69 -> 4720.4645 | H72: =H67-H69 -> 4215.3196 | I72: =I67-I69 -> 3656.8496
B74: Term B
B75: BOY balance | E75: =E14 -> 1438.43 | F75: =E78 -> 1438.43 | G75: =F78 -> 1438.43 | H75: =G78 -> 1438.43 | I75: =H78 -> 1438.43
B76: Interest paid | E76: =E75*$F$14 -> 107.88225 | F76: =F75*$F$14 -> 107.88225 | G76: =G75*$F$14 -> 107.88225 | H76: =H75*$F$14 -> 107.88225 | I76: =I75*$F$14 -> 107.88225
B77: Principal repaid | E77: =E69-E90 -> 0 | F77: =F69-F90 -> 0 | G77: =G69-G90 -> 0 | H77: =H69-H90 -> 0 | I77: =I69-I90 -> 0
B78: EOY balance | E78: =E75-E77 -> 1438.43 | F78: =F75-F77 -> 1438.43 | G78: =G75-G77 -> 1438.43 | H78: =H75-H77 -> 1438.43 | I78: =I75-I77 -> 1438.43
B80: Cash available after Senior Debt & Unsecured Debt | E80: =E36-E68-E76 -> 257.69515 | F80: =F36-F68-F76 -> 516.92988 | G80: =G36-G68-G76 -> 520.26884 | H80: =H36-H68-H76 -> 665.1592 | I80: =I36-I68-I76 -> 729.76517
B82: Mezzanine
B83: BOY balance | E83: =E15 -> 2876.86 | F83: =E86 -> 2934.3972 | G83: =F86 -> 2993.0851 | H83: =G86 -> 3052.9468 | I83: =H86 -> 3114.0058
B84: Interest paid | E84: =E83*$F$15 -> 316.4546 | F84: =F83*$F$15 -> 322.78369 | G84: =G83*$F$15 -> 329.23937 | H84: =H83*$F$15 -> 335.82415 | I84: =I83*$F$15 -> 342.54064
B85: PIK | E85: =E83*$G$15 -> 57.5372 | F85: =F83*$G$15 -> 58.687944 | G85: =G83*$G$15 -> 59.861703 | H85: =H83*$G$15 -> 61.058937 | I85: =I83*$G$15 -> 62.280116
B86: EOY balance | E86: =E83+E85 -> 2934.3972 | F86: =F83+F85 -> 2993.0851 | G86: =G83+G85 -> 3052.9468 | H86: =H83+H85 -> 3114.0058 | I86: =I83+I85 -> 3176.2859
B88: Total cash interest paid | E88: =E68+E76+E84 -> 740.79145 | F88: =F68+F76+F84 -> 731.29781 | G88: =G68+G76+G84 -> 717.08213 | H88: =H68+H76+H84 -> 703.33195 | I88: =I68+I76+I84 -> 682.26546
B89: Interest tax shield | E89: =(E88+E85)*$D$8 -> 183.61559 | F89: =(F88+F85)*$D$8 -> 181.69672 | G89: =(G88+G85)*$D$8 -> 178.69708 | H89: =(H88+H85)*$D$8 -> 175.8099 | I89: =(I88+I85)*$D$8 -> 171.24548
B90: Cash flows available for debt repayment | E90: =E36-E88+E89 -> 124.85614 | F90: =F36-F88+F89 -> 375.84291 | G90: =G36-G88+G89 -> 369.72655 | H90: =H36-H88+H89 -> 505.14495 | I90: =I36-I88+I89 -> 558.47002
B91: Total debt outstanding | E91: =E72+E78+E86 -> 9838.8612 | F91: =F72+F78+F86 -> 9521.7062 | G91: =G72+G78+G86 -> 9211.8414 | H91: =H72+H78+H86 -> 8767.7554 | I91: =I72+I78+I86 -> 8271.5655
B93: Beginning Cash | E93: =D9 -> 0 | F93: =E95 -> 0 | G93: =F95 -> 0 | H93: =G95 -> 0 | I93: =H95 -> 0
B94: Change in cash | E94: =E36-E88-E69+E89 -> 0 | F94: =F36-F88-F69+F89 -> 0 | G94: =G36-G88-G69+G89 -> 0 | H94: =H36-H88-H69+H89 -> 0 | I94: =I36-I88-I69+I89 -> 0
B95: Ending Cash | E95: =E93+E94 -> 0 | F95: =F93+F94 -> 0 | G95: =G93+G94 -> 0 | H95: =H93+H94 -> 0 | I95: =I93+I94 -> 0
B97: Step 4: Return Calculation
B98: Williams-Sonoma, Inc., LBO: Let’s Get Cooking
E99: Exit Year
E100: 1 | F100: 2 | G100: 3 | H100: 4 | I100: 5
B101: Exit Multiple (EV / LTM EBITDA) | D101: =I6 -> 9 | E101: =E29*$D$101 -> 12945.87 | F101: =F29*$D$101 -> 13326.12 | G101: =G29*$D$101 -> 13291.47 | H101: =H29*$D$101 -> 15413.49 | I101: =I29*$D$101 -> 16171.83
B103: Debt | E103: =E91 -> 9838.8612 | F103: =F91 -> 9521.7062 | G103: =G91 -> 9211.8414 | H103: =H91 -> 8767.7554 | I103: =I91 -> 8271.5655
B104: Cash | E104: =E95 -> 0 | F104: =F95 -> 0 | G104: =G95 -> 0 | H104: =H95 -> 0 | I104: =I95 -> 0
B105: Equity Value | E105: =E101-E103+E104 -> 3107.0088 | F105: =F101-F103+F104 -> 3804.4138 | G105: =G101-G103+G104 -> 4079.6286 | H105: =H101-H103+H104 -> 6645.7346 | I105: =I101-I103+I104 -> 7900.2645
B107: IRR | E107: =(E105/$E$16)^(1/E100)-1 -> 0.08 | F107: =(F105/$E$16)^(1/F100)-1 -> 0.1499647 | G107: =(G105/$E$16)^(1/G100)-1 -> 0.12348506 | H107: =(H105/$E$16)^(1/H100)-1 -> 0.23283816 | I107: =(I105/$E$16)^(1/I100)-1 -> 0.22389619
B108: MOIC (Multiple on invested Capital) | E108: =E105/$E$16 -> 1.08 | F108: =F105/$E$16 -> 1.3224188 | G108: =G105/$E$16 -> 1.4180838 | H108: =H105/$E$16 -> 2.3100654 | I108: =I105/$E$16 -> 2.7461415
B111: Cavalier Capital
B112: Equity stake of mezzanine investors | I112: 0.05
B113: Equity value to mezzanine investors | I113: =+I105*I112 -> 395.01323
B114: Cash flows for mezzanine investors | D114: =-E15 -> -2876.86 | E114: =E84 -> 316.4546 | F114: =F84 -> 322.78369 | G114: =G84 -> 329.23937 | H114: =H84 -> 335.82415 | I114: =I84+MIN(I86,I101-I78-I72)+I113 -> 3913.8398
B115: Mezzanine internal rate of return (IRR) | D115: =IRR(D114:I114) -> 0.1496862
B116: Mezzanine cash on cash | D116: =SUM(E114:I114)/-D114 -> 1.8138323
B118: Jefferson Capital Management
B119: Cash flows for equity investors | D119: =-E16 -> -2876.86 | E119: 0 | F119: 0 | G119: 0 | H119: 0 | I119: =I105-I113 -> 7505.2513
B120: Equity IRR | D120: =IRR(D119:I119) -> 0.21140483
B121: Equity cash on cash | D121: =SUM(E119:I119)/-D119 -> 2.6088344
B124: Step 5: Sensitivity Analysis
F126: Cavalier Capital
C127: IRR of Equity Investment
...

Sheet LBO Model- 3x Debt A
A1: Luke Buddie, Gennaro Di Mauro, Peter Spira, Caden Carney
B3: Step 1: Outline everything you know
B4: Williams-Sonoma, Inc., LBO: Let’s Get Cooking
B5: Assumptions
B7: 2024 EBITDA | D7: ='Ex 10 Projections'!E18 -> 1438.43 | E7: Exhibit 10 | H7: Exit multiple | I7: =D13 -> 8
B8: SOFR | D8: 0.03 | H8: Number of shares outstanding (in millions) | I8: ='Ex 11 Comps'!I16 -> 64.2 | J8: Exhibit 11
B9: Tax rate | D9: 0.23 | E9: Exhibit 10 | H9: Current enterprise value | I9: =('Ex 11 Comps'!I16*'Ex 11 Comps'!J16)+'Ex 11 Comps'!K16 -> 8758.648 | J9: Equity Value + Debt Value
B10: Opening Balance Cash | D10: 0 | E10: Exhibit 9 - Case
B12: Financing Package | E12: Amount | F12: Cash Interest | G12: PIK | J12: SOFR +
B13: Purchase multiple | D13: =SUM(D14:D17) -> 8 | E13: =D7*D13 -> 11507.44
B14: Term A | D14: 3 | E14: =D14*$D$7 -> 4315.29 | F14: =D8+J14 -> 0.055 | J14: 0.025
B15: Term B | D15: 1 | E15: =D15*$D$7 -> 1438.43 | F15: =D8+J15 -> 0.075 | J15: 0.045
B16: Mezzanine (Cavalier Capital) | D16: 2 | E16: =D16*$D$7 -> 2876.86 | F16: 0.11 | G16: 0.02 | J16: Minimum Priciple
B17: Equity investment (Jeffereson Capital Management) | D17: 2 | E17: =E13-E14-E15-E16 -> 2876.86 | J17: 0.05
B20: Step 2: How/Who are you going to pay down your debt with your free cash flow?
B21: Williams-Sonoma, Inc., LBO: Let’s Get Cooking
B22: Debt-Repayment Schedule | K22: Target Leverage
K23: Debt/EBITDA: 4-6x
D24: 2023 | E24: 2024 | F24: 2025 | G24: 2026 | H24: 2027 | I24: 2028
B25: ='Ex 10 Projections'!B11 -> Total revenue | D25: ='Ex 10 Projections'!D11 -> 8674.42 | E25: ='Ex 10 Projections'!E11 -> 8471 | F25: ='Ex 10 Projections'!F11 -> 8553 | G25: ='Ex 10 Projections'!G11 -> 8862.29 | H25: ='Ex 10 Projections'!H11 -> 9181.33 | I25: ='Ex 10 Projections'!I11 -> 9582.61
B26: ='Ex 10 Projections'!B12 -> Cost of goods sold | D26: ='Ex 10 Projections'!D12 -> 4996.68 | E26: ='Ex 10 Projections'!E12 -> 5067.8 | F26: ='Ex 10 Projections'!F12 -> 5082.1 | G26: ='Ex 10 Projections'!G12 -> 5241.16 | H26: ='Ex 10 Projections'!H12 -> 5407.8 | I26: ='Ex 10 Projections'!I12 -> 5605.83
B27: ='Ex 10 Projections'!B13 -> Gross profit | D27: =D25-D26 -> 3677.74 | E27: =E25-E26 -> 3403.2 | F27: =F25-F26 -> 3470.9 | G27: =G25-G26 -> 3621.13 | H27: =H25-H26 -> 3773.53 | I27: =I25-I26 -> 3976.78
B28: ='Ex 10 Projections'!B14 -> Selling, general, and administrative expenses | D28: ='Ex 10 Projections'!D14 -> 2179.31 | E28: ='Ex 10 Projections'!E14 -> 2189.6 | F28: ='Ex 10 Projections'!F14 -> 2223.7 | G28: ='Ex 10 Projections'!G14 -> 2395.05 | H28: ='Ex 10 Projections'!H14 -> 2313.43 | I28: ='Ex 10 Projections'!I14 -> 2443.78
B29: ='Ex 10 Projections'!B17 -> Depreciation and amortization | D29: ='Ex 10 Projections'!D17 -> 214.2 | E29: ='Ex 10 Projections'!E17 -> 224.83 | F29: ='Ex 10 Projections'!F17 -> 233.48 | G29: ='Ex 10 Projections'!G17 -> 250.75 | H29: ='Ex 10 Projections'!H17 -> 252.51 | I29: ='Ex 10 Projections'!I17 -> 263.87
B30: ='Ex 10 Projections'!B18 -> EBITDA | D30: =(D27-D28+D29) -> 1712.63 | E30: =(E27-E28+E29) -> 1438.43 | F30: =(F27-F28+F29) -> 1480.68 | G30: =(G27-G28+G29) -> 1476.83 | H30: =(H27-H28+H29) -> 1712.61 | I30: =(I27-I28+I29) -> 1796.87
B31: Haircut to EBITDA (difference from expected EBITDA vs. realitstic) | C31: 0 | D31: =D30*(1+$C$31) -> 1712.63 | E31: =E30*(1+$C$31) -> 1438.43 | F31: =F30*(1+$C$31) -> 1480.68 | G31: =G30*(1+$C$31) -> 1476.83 | H31: =H30*(1+$C$31) -> 1712.61 | I31: =I30*(1+$C$31) -> 1796.87
B33: ='Ex 10 Projections'!B15 -> Operating income (EBIT) | D33: =D31-D29 -> 1498.43 | E33: =E31-E29 -> 1213.6 | F33: =F31-F29 -> 1247.2 | G33: =G31-G29 -> 1226.08 | H33: =H31-H29 -> 1460.1 | I33: =I31-I29 -> 1533
B34: ='Ex 10 Projections'!B22 -> CAPEX | D34: ='Ex 10 Projections'!D22 -> 354.1 | E34: ='Ex 10 Projections'!E22 -> 249.4 | F34: ='Ex 10 Projections'!F22 -> 262.31 | G34: ='Ex 10 Projections'!G22 -> 263.81 | H34: ='Ex 10 Projections'!H22 -> 320.49 | I34: ='Ex 10 Projections'!I22 -> 345.07
B35: ='Ex 10 Projections'!B23 -> Change in net working capital (NWC) | D35: ='Ex 10 Projections'!D23 -> -152.6 | E35: ='Ex 10 Projections'!E23 -> 227.87 | F35: ='Ex 10 Projections'!F23 -> 6.07 | G35: ='Ex 10 Projections'!G23 -> 22.91 | H35: ='Ex 10 Projections'!H23 -> 23.63 | I35: ='Ex 10 Projections'!I23 -> 29.72
B37: FCF | E37: =E33*(1-$D$9)+E29-E34-E35 -> 682.032 | F37: =F33*(1-$D$9)+F29-F34-F35 -> 925.444 | G37: =G33*(1-$D$9)+G29-G34-G35 -> 908.1116 | H37: =H33*(1-$D$9)+H29-H34-H35 -> 1032.667 | I37: =I33*(1-$D$9)+I29-I34-I35 -> 1069.49
B38: Beginning Balance | E38: =E14 -> 4315.29 | F38: =E38-E39 -> 4099.5255 | G38: =F38-F39 -> 3883.761 | H38: =G38-G39 -> 3667.9965 | I38: =H38-H39 -> 3452.232
B39: Team A FCC (4x, 3x, 2x) Principal | E39: =$J$17*$E$38 -> 215.7645 | F39: =$J$17*$E$38 -> 215.7645 | G39: =$J$17*$E$38 -> 215.7645 | H39: =$J$17*$E$38 -> 215.7645 | I39: =$J$17*$E$38 -> 215.7645
B40: Interest | E40: =$F$14*E38 -> 237.34095 | F40: =$F$14*F38 -> 225.4739 | G40: =$F$14*G38 -> 213.60685 | H40: =$F$14*H38 -> 201.73981 | I40: =$F$14*I38 -> 189.87276
B42: Total Debt | E42: =E39+E40 -> 453.10545 | F42: =F39+F40 -> 441.2384 | G42: =G39+G40 -> 429.37135 | H42: =H39+H40 -> 417.50431 | I42: =I39+I40 -> 405.63726
B43: Tax shield | E43: =E40*$D$9 -> 54.588419 | F43: =F40*$D$9 -> 51.858998 | G43: =G40*$D$9 -> 49.129577 | H43: =H40*$D$9 -> 46.400156 | I43: =I40*$D$9 -> 43.670735
B44: Excess Cash Flow | E44: =E37-E42+E43 -> 283.51497 | F44: =F37-F42+F43 -> 536.0646 | G44: =G37-G42+G43 -> 527.86982 | H44: =H37-H42+H43 -> 661.56285 | I44: =I37-I42+I43 -> 707.52347
B45: FCC | E45: =(E42+E44)/E42 -> 1.6257152 | F45: =(F42+F44)/F42 -> 2.2149092 | G45: =(G42+G44)/G42 -> 2.2294016 | H45: =(H42+H44)/H42 -> 2.5845653 | I45: =(I42+I44)/I42 -> 2.744227
B47: Term B
B48: FCF | E48: =E44 -> 283.51497 | F48: =F44 -> 536.0646 | G48: =G44 -> 527.86982 | H48: =H44 -> 661.56285 | I48: =I44 -> 707.52347
B49: No principal
B50: Interest | E50: =$F$15*$E$15 -> 107.88225 | F50: =$F$15*$E$15 -> 107.88225 | G50: =$F$15*$E$15 -> 107.88225 | H50: =$F$15*$E$15 -> 107.88225 | I50: =$F$15*$E$15 -> 107.88225
B52: Total Debt | E52: =E50 -> 107.88225 | F52: =F50 -> 107.88225 | G52: =G50 -> 107.88225 | H52: =H50 -> 107.88225 | I52: =I50 -> 107.88225
B53: Tax Shield | E53: =E50*$D$9 -> 24.812918 | F53: =F50*$D$9 -> 24.812918 | G53: =G50*$D$9 -> 24.812918 | H53: =H50*$D$9 -> 24.812918 | I53: =I50*$D$9 -> 24.812918
B54: Excess | E54: =E48-E52+E53 -> 200.44564 | F54: =F48-F52+F53 -> 452.99526 | G54: =G48-G52+G53 -> 444.80049 | H54: =H48-H52+H53 -> 578.49352 | I54: =I48-I52+I53 -> 624.45414
B55: FCC | E55: =(E52+E54)/E52 -> 2.8580039 | F55: =(F52+F54)/F52 -> 5.1989786 | G55: =(G52+G54)/G52 -> 5.1230183 | H55: =(H52+H54)/H52 -> 6.3622678 | I55: =(I52+I54)/I52 -> 6.7882936
B57: Mezzanine | E57: =E54 -> 200.44564 | F57: =F54 -> 452.99526 | G57: =G54 -> 444.80049 | H57: =H54 -> 578.49352 | I57: =I54 -> 624.45414
B58: Interest | E58: =$F$16*$E$16 -> 316.4546 | F58: =$F$16*$E$16 -> 316.4546 | G58: =$F$16*$E$16 -> 316.4546 | H58: =$F$16*$E$16 -> 316.4546 | I58: =$F$16*$E$16 -> 316.4546
B59: Total Debt | E59: =E58 -> 316.4546 | F59: =F58 -> 316.4546 | G59: =G58 -> 316.4546 | H59: =H58 -> 316.4546 | I59: =I58 -> 316.4546
B60: Tax Shield | E60: =E59*$D$9 -> 72.784558 | F60: =F59*$D$9 -> 72.784558 | G60: =G59*$D$9 -> 72.784558 | H60: =H59*$D$9 -> 72.784558 | I60: =I59*$D$9 -> 72.784558
B61: Excess | E61: =E57-E59+E60 -> -43.224406 | F61: =F57-F59+F60 -> 209.32522 | G61: =G57-G59+G60 -> 201.13045 | H61: =H57-H59+H60 -> 334.82347 | I61: =I57-I59+I60 -> 380.7841
B62: FCC | E62: =(E61+E59)/E59 -> 0.8634104 | F62: =(F61+F59)/F59 -> 1.66147 | G62: =(G61+G59)/G59 -> 1.6355744 | H62: =(H61+H59)/H59 -> 2.0580458 | I62: =(I61+I59)/I59 -> 2.2032819
B66: Debt-repayment schedule
B67: Term A
B68: Beginning-of-year (BOY) balance | E68: =E14 -> 4315.29 | F68: =E73 -> 4099.5255 | G68: =F73 -> 3665.811 | H68: =G73 -> 3235.7619 | I68: =H73 -> 2667.7398
B69: Interest paid | E69: =E68*$F$14 -> 237.34095 | F69: =F68*$F$14 -> 225.4739 | G69: =G68*$F$14 -> 201.6196 | H69: =H68*$F$14 -> 177.9669 | I69: =I68*$F$14 -> 146.72569
B70: Principal repaid | E70: =IF(E68>E91, E91, E68) -> 185.77365 | F70: =IF(F68>F91, F91, F68) -> 433.71455 | G70: =IF(G68>G91, G91, G68) -> 430.04905 | H70: =IF(H68>H91, H91, H68) -> 568.02211 | I70: =IF(I68>I91, I91, I68) -> 624.01002
B71: Principal (5%) | E71: =$J$17*$E$14 -> 215.7645 | F71: =$J$17*$E$14 -> 215.7645 | G71: =$J$17*$E$14 -> 215.7645 | H71: =$J$17*$E$14 -> 215.7645 | I71: =$J$17*$E$14 -> 215.7645
B72: Sweep | E72: =IF(E70>288, E70-288, 0) -> 0 | F72: =IF(F70>288, F70-288, 0) -> 145.71455 | G72: =IF(G70>288, G70-288, 0) -> 142.04905 | H72: =IF(H70>288, H70-288, 0) -> 280.02211 | I72: =IF(I70>288, I70-288, 0) -> 336.01002
B73: End-of-year (EOY) balance | E73: =E68-(E71+E72) -> 4099.5255 | F73: =F68-F70 -> 3665.811 | G73: =G68-G70 -> 3235.7619 | H73: =H68-H70 -> 2667.7398 | I73: =I68-I70 -> 2043.7298
B75: Term B
B76: BOY balance | E76: =E15 -> 1438.43 | F76: =E79 -> 1438.43 | G76: =F79 -> 1438.43 | H76: =G79 -> 1438.43 | I76: =H79 -> 1438.43
B77: Interest paid | E77: =E76*$F$15 -> 107.88225 | F77: =F76*$F$15 -> 107.88225 | G77: =G76*$F$15 -> 107.88225 | H77: =H76*$F$15 -> 107.88225 | I77: =I76*$F$15 -> 107.88225
B78: Principal repaid | E78: =E70-E91 -> 0 | F78: =F70-F91 -> 0 | G78: =G70-G91 -> 0 | H78: =H70-H91 -> 0 | I78: =I70-I91 -> 0
B79: EOY balance | E79: =E76-E78 -> 1438.43 | F79: =F76-F78 -> 1438.43 | G79: =G76-G78 -> 1438.43 | H79: =H76-H78 -> 1438.43 | I79: =I76-I78 -> 1438.43
B81: Cash available after Senior Debt & Unsecured Debt | E81: =E37-E69-E77 -> 336.8088 | F81: =F37-F69-F77 -> 592.08785 | G81: =G37-G69-G77 -> 598.60975 | H81: =H37-H69-H77 -> 746.81785 | I81: =I37-I69-I77 -> 814.88206
B83: Mezzanine
B84: BOY balance | E84: =E16 -> 2876.86 | F84: =E87 -> 2934.3972 | G84: =F87 -> 2993.0851 | H84: =G87 -> 3052.9468 | I84: =H87 -> 3114.0058
B85: Interest paid | E85: =E84*$F$16 -> 316.4546 | F85: =F84*$F$16 -> 322.78369 | G85: =G84*$F$16 -> 329.23937 | H85: =H84*$F$16 -> 335.82415 | I85: =I84*$F$16 -> 342.54064
B86: PIK | E86: =E84*$G$16 -> 57.5372 | F86: =F84*$G$16 -> 58.687944 | G86: =G84*$G$16 -> 59.861703 | H86: =H84*$G$16 -> 61.058937 | I86: =I84*$G$16 -> 62.280116
B87: EOY balance | E87: =E84+E86 -> 2934.3972 | F87: =F84+F86 -> 2993.0851 | G87: =G84+G86 -> 3052.9468 | H87: =H84+H86 -> 3114.0058 | I87: =I84+I86 -> 3176.2859
B89: Total cash interest paid | E89: =E69+E77+E85 -> 661.6778 | F89: =F69+F77+F85 -> 656.13984 | G89: =G69+G77+G85 -> 638.74122 | H89: =H69+H77+H85 -> 621.67331 | I89: =I69+I77+I85 -> 597.14857
B90: Interest tax shield | E90: =(E89+E86)*$D$9 -> 165.41945 | F90: =(F89+F86)*$D$9 -> 164.41039 | G90: =(G89+G86)*$D$9 -> 160.67867 | H90: =(H89+H86)*$D$9 -> 157.02842 | I90: =(I89+I86)*$D$9 -> 151.6686
B91: Cash flows available for debt repayment | E91: =E37-E89+E90 -> 185.77365 | F91: =F37-F89+F90 -> 433.71455 | G91: =G37-G89+G90 -> 430.04905 | H91: =H37-H89+H90 -> 568.02211 | I91: =I37-I89+I90 -> 624.01002
B92: Total debt outstanding | E92: =E73+E79+E87 -> 8472.3527 | F92: =F73+F79+F87 -> 8097.3261 | G92: =G73+G79+G87 -> 7727.1387 | H92: =H73+H79+H87 -> 7220.1756 | I92: =I73+I79+I87 -> 6658.4457
B94: Beginning Cash | E94: =D10 -> 0 | F94: =E96 -> 0 | G94: =F96 -> 0 | H94: =G96 -> 0 | I94: =H96 -> 0
B95: Change in cash | E95: =E37-E89-E70+E90 -> 0 | F95: =F37-F89-F70+F90 -> 0 | G95: =G37-G89-G70+G90 -> 0 | H95: =H37-H89-H70+H90 -> 0 | I95: =I37-I89-I70+I90 -> 0
B96: Ending Cash | E96: =E94+E95 -> 0 | F96: =F94+F95 -> 0 | G96: =G94+G95 -> 0 | H96: =H94+H95 -> 0 | I96: =I94+I95 -> 0
B98: Step 4: Return Calculation
B99: Williams-Sonoma, Inc., LBO: Let’s Get Cooking
E100: Exit Year
E101: 1 | F101: 2 | G101: 3 | H101: 4 | I101: 5
B102: Exit Multiple (EV / LTM EBITDA) | D102: =I7 -> 8 | E102: =E30*$D$102 -> 11507.44 | F102: =F30*$D$102 -> 11845.44 | G102: =G30*$D$102 -> 11814.64 | H102: =H30*$D$102 -> 13700.88 | I102: =I30*$D$102 -> 14374.96
B104: Debt | E104: =E92 -> 8472.3527 | F104: =F92 -> 8097.3261 | G104: =G92 -> 7727.1387 | H104: =H92 -> 7220.1756 | I104: =I92 -> 6658.4457
B105: Cash | E105: =E96 -> 0 | F105: =F96 -> 0 | G105: =G96 -> 0 | H105: =H96 -> 0 | I105: =I96 -> 0
B106: Equity Value | E106: =E102-E104+E105 -> 3035.0873 | F106: =F102-F104+F105 -> 3748.1139 | G106: =G102-G104+G105 -> 4087.5013 | H106: =H102-H104+H105 -> 6480.7044 | I106: =I102-I104+I105 -> 7716.5143
B108: IRR | E108: =(E106/$E$17)^(1/E101)-1 -> 0.055 | F108: =(F106/$E$17)^(1/F101)-1 -> 0.14142407 | G108: =(G106/$E$17)^(1/G101)-1 -> 0.12420727 | H108: =(H106/$E$17)^(1/H101)-1 -> 0.22511222 | I108: =(I106/$E$17)^(1/I101)-1 -> 0.21814921
B109: MOIC (Multiple on invested Capital) | E109: =E106/$E$17 -> 1.055 | F109: =F106/$E$17 -> 1.3028489 | G109: =G106/$E$17 -> 1.4208204 | H109: =H106/$E$17 -> 2.2527007 | I109: =I106/$E$17 -> 2.6822697
B112: Cavalier Capital
B113: Equity stake of mezzanine investors | I113: 0.05
B114: Equity value to mezzanine investors | I114: =+I106*I113 -> 385.82572
B115: Cash flows for mezzanine investors | D115: =-E16 -> -2876.86 | E115: =E85 -> 316.4546 | F115: =F85 -> 322.78369 | G115: =G85 -> 329.23937 | H115: =H85 -> 335.82415 | I115: =I85+MIN(I87,I102-I79-I73)+I114 -> 3904.6523
B116: Mezzanine internal rate of return (IRR) | D116: =IRR(D115:I115) -> 0.14924485
B117: Mezzanine cash on cash | D117: =SUM(E115:I115)/-D115 -> 1.8106387
B119: Jefferson Capital Management
B120: Cash flows for equity investors | D120: =-E17 -> -2876.86 | E120: 0 | F120: 0 | G120: 0 | H120: 0 | I120: =I106-I114 -> 7330.6886
B121: Equity IRR | D121: =IRR(D120:I120) -> 0.20571651
B122: Equity cash on cash | D122: =SUM(E120:I120)/-D120 -> 2.5481562
B125: Step 5: Sensitivity Analysis
F127: Cavalier Capital
C128: IRR of Equity Investment
...

Sheet Hayden Notes
B3: Financing Package is based on Case information
B6: Hayden's Free Cash Flows
B7: 2024 | C7: 682.032
B8: 2025 | C8: 925.444
B9: 2026 | C9: 908.1116
B10: 2027 | C10: 1032.667
B11: 2028 | C11: 1069.49
B13: Cash Interest is outlined in the case. It's SOFR + Something
B14: BPS = Basis Points. 100 bps = 1.00%
B15: SOFR = Secured Overnight Financing Rate.
B16: PIK = paid in kind.
B17: EBIT = earnings before interest and taxes.
B18: CAPEX = capital expenditure.

Sheet Ex 10 Projections
B1: Exhibit 10
B2: Williams-Sonoma, Inc., LBO: Let’s Get Cooking
B3: Williams-Sonoma: Financial Forecast
B5: Fiscal period ending January (in millions of US dollars) | C5: 44592 | D5: 44957 | E5: 45322 | F5: 45688 | G5: 46053 | H5: 46418 | I5: 46783
B6: Pottery Barn | C6: 3120.69 | D6: 3555.52 | E6: 3469 | F6: 3414 | G6: 3537.46 | H6: 3664.8 | I6: 3824.98
B7: West Elm | C7: 2234.55 | D7: 2278.13 | E7: 2277 | F7: 2454 | G7: 2542.74 | H7: 2634.28 | I7: 2749.41
B8: Williams Sonoma | C8: 1345.85 | D8: 1286.65 | E8: 1244 | F8: 1224 | G8: 1268.26 | H8: 1313.92 | I8: 1371.35
B9: Pottery Barn Kids and Teen | C9: 1139.89 | D9: 1132.94 | E9: 1052 | F9: 998 | G9: 1034.09 | H9: 1071.32 | I9: 1118.14
B10: Other | C10: 404.96 | D10: 421.18 | E10: 429 | F10: 463 | G10: 479.74 | H10: 497.01 | I10: 518.74
B11: Total revenue | C11: 8245.94 | D11: 8674.42 | E11: 8471 | F11: 8553 | G11: 8862.29 | H11: 9181.33 | I11: 9582.61
B12: Cost of goods sold | C12: 4613.97 | D12: 4996.68 | E12: 5067.8 | F12: 5082.1 | G12: 5241.16 | H12: 5407.8 | I12: 5605.83
B13: Gross profit | C13: 3631.96 | D13: 3677.73 | E13: 3403.2 | F13: 3470.9 | G13: 3621.13 | H13: 3773.53 | I13: 3976.78
B14: Selling, general, and administrative expenses | C14: 2178.85 | D14: 2179.31 | E14: 2189.6 | F14: 2223.7 | G14: 2395.05 | H14: 2313.43 | I14: 2443.78
B15: Operating income (EBIT) | C15: 1453.12 | D15: 1498.42 | E15: 1213.6 | F15: 1247.2 | G15: 1226.08 | H15: 1460.1 | I15: 1533
B17: Depreciation and amortization | C17: 196.1 | D17: 214.2 | E17: 224.83 | F17: 233.48 | G17: 250.75 | H17: 252.51 | I17: 263.87
... B23: Change in net working capital (NWC) | C23: -366.3 | D23: -152.6 | E23: 227.87 | F23: 6.07 | G23: 22.91 | H23: 23.63 | I23: 29.72
B26: ¹ Tax rate is 23%.
B27: Note: Data is for 12 months ending January 31 of each year.
B28: EBIT = earnings before interest and taxes.
B29: NOPAT = net operating profit after tax.
B30: CAPEX = capital expenditure.
B32: Data source: Capital IQ and analyst estimates.

Sheet Ex 11 Comps
B1: Exhibit 11
B2: Williams-Sonoma, Inc., LBO: Let’s Get Cooking
B3: Comparable Companies Analysis
B5: Company Name | C5: Sales | D5: EBITDA | E5: EBIT | F5: Year-over-Year (YoY) Sales Growth | G5: YoY EBITDA Growth | H5: YoY EBIT Growth | I5: Number of Shares | J5: Price per Share | K5: Debt | L5: Cash | M5: Beta | N5: Enterprise Value/ EBITDA | O5: Debt/EBITDA
B6: RH (NYSE:RH) | C6: 3590.5 | D6: 839.7 | E6: 731.2 | F6: -0.044774928 | G6: -0.18736088 | H6: -0.21988691 | I6: 22.1 | J6: 244.64 | K6: 3749.5 | L6: 1508.1 | M6: 2.08 | N6: =(I6*J6+K6-L6)/D6 -> 9.1079481 | O6: =K6/D6 -> 4.4652852
B7: Sleep Number Corporation (NasdaqGS:SNBR) | C7: 2114.3 | D7: 133.3 | E7: 67.9 | F7: -0.032312692 | G7: -0.47082175 | H7: -0.64909561 | I7: 22.2 | J7: 18.1 | K7: 896 | L7: 1.79 | M7: 1.83 | N7: =(I7*J7+K7-L7)/D7 -> 9.7226557 | O7: =K7/D7 -> 6.7216804
B8: Lowe’s Companies, Inc. (NYSE:LOW) | C8: 97059 | D8: 14201 | E8: 12220 | F8: 0.0084051948 | G8: 0.016171735 | H8: 0.010501943 | I8: 592 | J8: 203.92 | K8: 38082 | L8: 1983 | M8: 1.07 | N8: =(I8*J8+K8-L8)/D8 -> 11.042859 | O8: =K8/D8 -> 2.6816421 | P8: =AVERAGE(O6:O14) -> 1.2888821 | Q8: AVG
B9: The Home Depot, Inc. (NYSE:HD) | C9: 157403 | D9: 27014 | E9: 24039 | F9: 0.041321275 | G9: 0.042931048 | H9: 0.043359375 | I9: 1005.4 | J9: 288.39 | K9: 50364 | L9: 2757 | M9: 0.93 | N9: =(I9*J9+K9-L9)/D9 -> 12.495532 | O9: =K9/D9 -> 1.8643666
B10: Bed Bath & Beyond Inc. (OTCPK:BBBY.Q) | C10: 6210.9 | D10: -612.7 | E10: -922.6 | F10: -0.26371881 | G10: -2.6234764 | H10: -11.944247 | I10: 466 | J10: 0.26 | K10: 3698.7 | L10: 153.52 | M10: 1.45 | O10: =K10/D10 -> -6.0367227
B11: Tractor Supply Company (NasdaqGS:TSCO) | C11: 14204.7 | D11: 1778 | E11: 1434.9 | F11: 0.11574805 | G11: 0.1275287 | H11: 0.098109742 | I11: 109.6 | J11: 206.32 | K11: 4270.2 | L11: 202.5 | M11: 0.82 | N11: =(I11*J11+K11-L11)/D11 -> 15.005834 | O11: =K11/D11 -> 2.4016873
B12: Overstock.com, Inc. (NasdaqGM:OSTK) | C12: 1929.3 | D12: 37.1 | E12: 27 | F12: -0.3000653 | G12: -0.69689542 | H12: -0.7569757 | I12: 45.2 | J12: 18.81 | K12: 46 | L12: 371.26 | M12: 3.37 | N12: =(I12*J12+K12-L12)/D12 -> 14.14965 | O12: =K12/D12 -> 1.2398922
B13: Wayfair Inc. (NYSE:W) | C13: 12218 | D13: -1167 | E13: -1314 | F13: -0.10869565 | G13: -17.913043 | H13: 15.02439 | I13: 112.3 | J13: 43.01 | K13: 4155 | L13: 1278 | M13: 3.01 | O13: =K13/D13 -> -3.5604113
B14: Arhaus, Inc. (NasdaqGS:ARHS) | C14: 1228.9 | D14: 209.6 | E14: 184.7 | F14: 0.54210064 | G14: 2.1097923 | H14: 3.245977 | I14: 140 | J14: 6.81 | K14: 382 | L14: 145.18 | M14: NA | N14: =(I14*J14+K14-L14)/D14 -> 5.6785305 | O14: =K14/D14 -> 1.8225191
B16: Williams-Sonoma, Inc. (NYSE:WSM) | C16: 8674.4 | D16: 1728.2 | E16: 1514 | F16: 0.051965219 | G16: 0.047902013 | H16: 0.041910398 | I16: 64.2 | J16: 113.94 | K16: 1443.7 | L16: 367.34 | M16: 1.59 | N16: =(I16*J16+K16)/D16 -> 5.0680755
B18: Financial data as of December 31, 2022; market data as of June 1, 2023.
B19: Beta is calculated using five-year historical data.
B20: All financials have been adjusted to represent 12-month calendar year financials based on respective fiscal year ends.
B22: Data source: Capital IQ.
